Workbook

Sheet Sheet2
A3: 销售订单号 | B3: 求和项:收款金额
A4: 20251015000059 | B4: 2950
A5: 20251027005412 | B5: 8055
A6: A20051025002418 | B6: 770
A7: A20250705000781C | B7: 2951
A8: A20250710003461C | B8: 2745
A9: A20250712005748C | B9: 2450
A10: A20250717001898C | B10: 3247
A11: A20250718002949C | B11: 2542
A12: A20250719001685C | B12: 2975
A13: A20250720003712C | B13: 5098
A14: A20250802002197C | B14: 4124
A15: A20250803001634C | B15: 5988
... A101: A20251012005268 | B101: 4764
A102: A20251012005314
A103: A20251013000189 | B103: 4289
A104: A20251013000313 | B104: 4481
A105: A20251013000424 | B105: 2071
A106: A20251013000458 | B106: 4086
A107: A20251013000973 | B107: 1340
A108: A20251013000974 | B108: 3395
A109: A20251013001055 | B109: 5872
A110: A20251013001594 | B110: 4279
A111: A20251013002496 | B111: 4400
A112: A20251013002814 | B112: 898
A113: A20251014000230 | B113: 6440
A114: A20251014000643 | B114: 5100
... A165: A20251020003506 | B165: 3060
A166: A20251020003601
A167: A20251021001704 | B167: 2379
A168: A20251021002386 | B168: 4059
A169: A20251021002402 | B169: 3360
A170: A20251021003040 | B170: 790
A171: A20251021003315 | B171: 791
A172: A20251021003832 | B172: 4000
A173: A20251021004770 | B173: 2300
A174: A20251021005203 | B174: 5850
A175: A20251021005303 | B175: 2100
A176: A20251021005683 | B176: 898
A177: A20251021006855 | B177: 6291
A178: A20251021007440 | B178: 3636
... A188: A20251022002369 | B188: 398
A189: A20251022004134
A190: A20251023001176 | B190: 791
A191: A20251023001264
A192: A20251023001265 | B192: 5707
A193: A20251023001699 | B193: 3838
A194: A20251023001702 | B194: 2950
A195: A20251023001796 | B195: 4139
A196: A20251023001838 | B196: 1196
A197: A20251023001954 | B197: 5800
A198: A20251023002682 | B198: 2070
A199: A20251023003144 | B199: 4299
A200: A20251023006848 | B200: 890
A201: A20251024001610 | B201: 800
A202: A20251024004008 | B202: 6788
A203: A20251024004008C | B203: 6788
... A214: A20251025002496 | B214: 3136
A215: A20251025002531
A216: A20251025002627
A217: A20251025003123 | B217: 2984
A218: A20251025004987 | B218: 3395
A219: A20251025004988 | B219: 1196
A220: A20251025004989 | B220: 2079
A221: A20251025005260 | B221: 5988
A222: A20251025006127 | B222: 3369
A223: A20251025006186 | B223: 3395
A224: A20251026000929 | B224: 6700
A225: A20251026001008 | B225: 800
A226: A20251026001077 | B226: 4791
A227: A20251026001084 | B227: 1893
A228: A20251026001165 | B228: 5119
... A232: A20251026001509 | B232: 7200
A233: A20251026001513
A234: A20251026001965 | B234: 5000
A235: A20251026003004 | B235: 3990
A236: A20251026003114 | B236: 3138
A237: A20251026003656 | B237: 2984
A238: A20251026003658 | B238: 4295
A239: A20251026004463 | B239: 4020
A240: A20251026004787 | B240: 4180
A241: A20251026004812 | B241: 1895
A242: A20251026004927 | B242: 350
A243: A20251026005103 | B243: 4003
A244: A20251026006321 | B244: 4002
A245: A20251026006371 | B245: 3395
... A262: A20251027004349 | B262: 8000
A263: A20251027005308
A264: A20251027005351 | B264: 8006
A265: A20251028001446 | B265: 3908
A266: A20251028001483 | B266: 3636
A267: A20251028001642 | B267: 850
A268: A20251028001961 | B268: 2594
A269: A20251028002150 | B269: 3888
A270: A20251028003302 | B270: 3571
A271: A20251028004580 | B271: 5200
A272: A20251029001230 | B272: 3350
A273: A20251029003723 | B273: 2300
A274: A20251029004714 | B274: 4699
A275: A20251029004944 | B275: 2071
...

Sheet Sheet3
A3: 往来单位 | B3: 求和项:收款金额 | C3: 收款 | D3: 退款 | E3: 实际 | F3: 销管部
A4: 二轻专卖店以旧换新 | B4: 3745 | C4: 3745 | D4: =VLOOKUP(A4,[1]Sheet2!$A:$B,2,0) -> 1000 | E4: =C4-D4 -> 2745 | F4: =VLOOKUP(A4,[2]杭州!$C:$BJ,60,0) -> #N/A
A5: （新）滨江第六空间专卖店 | B5: 109222 | C5: 109222 | D5: =VLOOKUP(A5,[1]Sheet2!$A:$B,2,0) -> 23893 | E5: =C5-D5 -> 85329 | F5: =VLOOKUP(A5,[2]杭州!$C:$BJ,60,0) -> 85329
A6: :衢州市柯城汇鑫家用电器商行以旧换新 | B6: 8388 | C6: 8388 | D6: =VLOOKUP(A6,[1]Sheet2!$A:$B,2,0) -> 8388 | E6: =C6-D6 -> 0 | F6: =VLOOKUP(A6,[2]杭州!$C:$BJ,60,0) -> #N/A
A7: 艾欧史密斯（中国）水系统有限公司 | B7: 15739.2 | C7: 15739.2 | E7: =C7-D7 -> 15739.2 | F7: =VLOOKUP(A7,[2]杭州!$C:$BJ,60,0) -> #N/A
A8: 贝壳美家供应链管理（浙江）有限责任公司 | B8: 36202 | C8: 36202 | E8: =C8-D8 -> 36202 | F8: =VLOOKUP(A8,[2]杭州!$C:$BJ,60,0) -> 36202
A9: 滨江六空8090店 | B9: 326584 | C9: 326584 | D9: =VLOOKUP(A9,[1]Sheet2!$A:$B,2,0) -> 59722 | E9: =C9-D9 -> 266862 | F9: =VLOOKUP(A9,[2]杭州!$C:$BJ,60,0) -> 266862
A10: 杭州恒大建材超级旗舰店 | B10: 65384 | C10: 65384 | E10: =C10-D10 -> 65384 | F10: =VLOOKUP(A10,[2]杭州!$C:$BJ,60,0) -> 65384
A11: 杭州红星美凯龙一号店 | B11: 358655.6 | C11: 358655.6 | D11: =VLOOKUP(A11,[1]Sheet2!$A:$B,2,0) -> 58364.85 | E11: =C11-D11 -> 300290.75 | F11: =VLOOKUP(A11,[2]杭州!$C:$BJ,60,0) -> 300290.75
A12: 杭州宏信机电有限公司 | B12: 34000 | C12: 34000 | E12: =C12-D12 -> 34000 | F12: =VLOOKUP(A12,[2]杭州!$C:$BJ,60,0) -> 34000
A13: 杭州华东家电市场铁人电器商行 | B13: 1397.6 | C13: 1397.6 | E13: =C13-D13 -> 1397.6 | F13: =VLOOKUP(A13,[2]杭州!$C:$BJ,60,0) -> 1397.6
A14: 杭州金蝶零售 | B14: 344535.76 | C14: 344535.76 | D14: =VLOOKUP(A14,[1]Sheet2!$A:$B,2,0) -> 4400 | E14: =C14-D14 -> 340135.76 | F14: =VLOOKUP(A14,[2]杭州!$C:$BJ,60,0) -> 330288.06
A15: 杭州临安一栋电器有限公司 | B15: 40000 | C15: 40000 | E15: =C15-D15 -> 40000 | F15: =VLOOKUP(A15,[2]杭州!$C:$BJ,60,0) -> 40000
A16: 杭州临平江南家居专卖店 | B16: 55272 | C16: 55272 | D16: =VLOOKUP(A16,[1]Sheet2!$A:$B,2,0) -> 5988 | E16: =C16-D16 -> 49284 | F16: =VLOOKUP(A16,[2]杭州!$C:$BJ,60,0) -> 49284
A17: 杭州瑞艾工程技术服务有限公司 | B17: 9108.1 | C17: 9108.1 | E17: =C17-D17 -> 9108.1 | F17: =VLOOKUP(A17,[2]杭州!$C:$BJ,60,0) -> #N/A
A18: 杭州兴达京昀电器有限公司 | B18: 100000 | C18: 100000 | E18: =C18-D18 -> 100000 | F18: =VLOOKUP(A18,[2]杭州!$C:$BJ,60,0) -> 100000
A19: 杭州允选科技有限公司 | B19: 42126.63 | C19: 42126.63 | E19: =C19-D19 -> 42126.63 | F19: =VLOOKUP(A19,[2]杭州!$C:$BJ,60,0) -> 17360
A20: 杭州中博智能电器有限公司 | B20: 125003.28 | C20: 125003.28 | E20: =C20-D20 -> 125003.28 | F20: =VLOOKUP(A20,[2]杭州!$C:$BJ,60,0) -> 113351.28
A21: 杭州中瑞工程技术有限公司 | B21: 30887.28 | C21: 30887.28 | E21: =C21-D21 -> 30887.28 | F21: =VLOOKUP(A21,[2]杭州!$C:$BJ,60,0) -> 0
A22: 杭州装家百科电器有限公司 | B22: 4590 | C22: 4590 | E22: =C22-D22 -> 4590 | F22: =VLOOKUP(A22,[2]杭州!$C:$BJ,60,0) -> 4590
A23: 湖州金蝶零售 | B23: 21969 | C23: 21969 | E23: =C23-D23 -> 21969 | F23: =VLOOKUP(A23,[2]杭州!$C:$BJ,60,0) -> #N/A
A24: 湖州浙北大厦家电有限公司 | B24: 150000 | C24: 150000 | E24: =C24-D24 -> 150000 | F24: =VLOOKUP(A24,[2]杭州!$C:$BJ,60,0) -> #N/A
A25: 湖州浙北网格家电有限公司 | B25: 24339 | C25: 24339 | E25: =C25-D25 -> 24339 | F25: =VLOOKUP(A25,[2]杭州!$C:$BJ,60,0) -> #N/A
A26: 嘉兴艾通电器有限公司 | B26: 36276.48 | C26: 36276.48 | E26: =C26-D26 -> 36276.48 | F26: =VLOOKUP(A26,[2]杭州!$C:$BJ,60,0) -> #N/A
A27: 金华龙腾建材市场专卖店 | B27: 68993 | C27: 68993 | D27: =VLOOKUP(A27,[1]Sheet2!$A:$B,2,0) -> 11868 | E27: =C27-D27 -> 57125 | F27: =VLOOKUP(A27,[2]杭州!$C:$BJ,60,0) -> #N/A
A28: 金华一启家电有限公司 | B28: 136.9 | C28: 136.9 | E28: =C28-D28 -> 136.9 | F28: =VLOOKUP(A28,[2]杭州!$C:$BJ,60,0) -> #N/A
A29: 京东五星电器集团宁波电器有限公司（台州） | B29: 71511.68 | C29: 71511.68 | E29: =C29-D29 -> 71511.68 | F29: =VLOOKUP(A29,[2]杭州!$C:$BJ,60,0) -> #N/A
A30: 兰溪市泽胜电器有限公司 | B30: 25150 | C30: 25150 | E30: =C30-D30 -> 25150 | F30: =VLOOKUP(A30,[2]杭州!$C:$BJ,60,0) -> #N/A
A31: 衢州市柯城汇鑫家用电器商行 | B31: 19913 | C31: 19913 | E31: =C31-D31 -> 19913 | F31: =VLOOKUP(A31,[2]杭州!$C:$BJ,60,0) -> #N/A
A32: 绍兴晨涛电器有限公司 | B32: 10970 | C32: 10970 | E32: =C32-D32 -> 10970 | F32: =VLOOKUP(A32,[2]杭州!$C:$BJ,60,0) -> #N/A
A33: 史密斯官方商城 | B33: 9287 | C33: 9287 | E33: =C33-D33 -> 9287 | F33: =VLOOKUP(A33,[2]杭州!$C:$BJ,60,0) -> #N/A
A34: 台州中嘉电器有限公司 | B34: 11543.15 | C34: 11543.15 | E34: =C34-D34 -> 11543.15 | F34: =VLOOKUP(A34,[2]杭州!$C:$BJ,60,0) -> #N/A
A35: 桐庐佳尼特水处理设备有限公司 | B35: 100000 | C35: 100000 | E35: =C35-D35 -> 100000 | F35: =VLOOKUP(A35,[2]杭州!$C:$BJ,60,0) -> 100000
A36: 温州吉远电器有限公司 | B36: 66047.06 | C36: 66047.06 | E36: =C36-D36 -> 66047.06 | F36: =VLOOKUP(A36,[2]杭州!$C:$BJ,60,0) -> #N/A
A37: 无人认领 | B37: 0.01 | C37: 0.01 | E37: =C37-D37 -> 0.01 | F37: =VLOOKUP(A37,[2]杭州!$C:$BJ,60,0) -> #N/A
A38: 萧山第六空间专卖店 | B38: 153067 | C38: 153067 | D38: =VLOOKUP(A38,[1]Sheet2!$A:$B,2,0) -> 29639 | E38: =C38-D38 -> 123428 | F38: =VLOOKUP(A38,[2]杭州!$C:$BJ,60,0) -> 126173
A39: 萧山汇德隆家电超市 | B39: 300000 | C39: 300000 | E39: =C39-D39 -> 300000 | F39: =VLOOKUP(A39,[2]杭州!$C:$BJ,60,0) -> #N/A
A40: 萧山汇德隆净水 | B40: 224728.9 | C40: 224728.9 | E40: =C40-D40 -> 224728.9 | F40: =VLOOKUP(A40,[2]杭州!$C:$BJ,60,0) -> 224728.9
A41: 义乌颖亿贸易有限公司 | B41: 8362 | C41: 8362 | E41: =C41-D41 -> 8362 | F41: =VLOOKUP(A41,[2]杭州!$C:$BJ,60,0) -> #N/A
A42: 永康市荣浪家用电器有限公司 | B42: 7490 | C42: 7490 | E42: =C42-D42 -> 7490 | F42: =VLOOKUP(A42,[2]杭州!$C:$BJ,60,0) -> #N/A
A43: 浙江都都装饰有限公司 | B43: 46864 | C43: 46864 | E43: =C43-D43 -> 46864 | F43: =VLOOKUP(A43,[2]杭州!$C:$BJ,60,0) -> 46864
A44: 浙江普农家电有限公司 | B44: 73131 | C44: 73131 | E44: =C44-D44 -> 73131 | F44: =VLOOKUP(A44,[2]杭州!$C:$BJ,60,0) -> #N/A
A45: 自营以旧换新特别账户 | B45: 547321 | C45: 547321 | D45: =VLOOKUP(A45,[1]Sheet2!$A:$B,2,0) -> 14976 | E45: =C45-D45 -> 532345 | F45: =VLOOKUP(A45,[2]杭州!$C:$BJ,60,0) -> #N/A
A46: (空白) | B46: 3687940.6
A47: 总计 | B47: 7375881.3 | C47: =SUM(C4:C46) -> 3687940.6 | D47: =SUM(D4:D46) -> 218238.85 | E47: =SUM(E4:E46) -> 3469701.8

Sheet Sheet1
A1: 单据类型 | B1: 单据编号 | C1: 客户所属区域 | D1: 业务日期 | E1: 往来单位类型 | F1: 付款单位类型 | G1: 币别 | H1: 表头-应收金额 | I1: 表头-实收金额 | J1: 结算组织 | K1: 部门 | L1: 销售组织 | M1: 往来单位 | N1: 销售部门 | O1: 销售组 | P1: 收款金额 | Q1: 销售员 | R1: 本位币 | S1: 汇率类型 | T1: 汇率 | U1: 表头-应收金额本位币 | V1: 表头-实收金额本位币 | W1: 会计核算体系 | X1: 核销状态 | Y1: 长短款本位币 | Z1: 业务类型 | AA1: 信用检查结果 | AB1: 结算方式 | AC1: 收款用途 | AD1: 预收项目类型 | AE1: 结算汇率 | AF1: 预收销售订单 | AG1: 表体-应收金额 | AH1: 现金折扣 | AI1: 表头-收款金额本位币 | AJ1: 折后金额 | AK1: 手续费 | AL1: 长短款 | AM1: 表体-实收金额 | AN1: 我方账户名称 | AO1: 是否期初单据 | AP1: 我方开户行 | AQ1: 来源系统 | AR1: 对方开户行 | AS1: 付款单位 | AT1: 结算号 | AU1: 对方银行账号 | AV1: 对方账户名称 | AW1: 现金折扣本位币 | AX1: 折后金额本位币 | AY1: 现销 | AZ1: 我方银行账号 | BA1: 表体-应收金额本位币 | BB1: 备注 | BC1: 勾对 | BD1: 关联总金额 | BE1: 表体明细-核销状态 | BF1: 表体明细-已核销金额 | BG1: 手续费本位币 | BH1: 表体-实收金额本位币 | BI1: 单据状态 | BJ1: 创建人 | BK1: 修改人 | BL1: 审核人 | BM1: 创建日期 | BN1: 修改日期 | BO1: 审核日期 | BP1: 作废人 | BQ1: 作废日期 | BR1: 作废状态 | BS1: 收款金额 | BT1: 内部账号 | BU1: 内部账户名称 | BV1: 现金账号 | BW1: 收款组织 | BX1: 退款关联金额 | BY1: 保证金转货款金额 | BZ1: 结算币别 | CA1: B2C业务 | CB1: 登账日期 | CC1: 是否登账 | CD1: 物料编码 | CE1: 物料名称 | CF1: 销售订单号 | CG1: 订单行号 | CH1: 是否转销 | CI1: 核销方式 | CJ1: 扫描点 | CK1: 备注 | CL1: 已核销金额本位币 | CM1: 第三方单据编号 | CN1: 结算本位币 | CO1: 结算汇率类型 | CP1: POS参考号 | CQ1: 收据号码 | CR1: 公司提单号 | CS1: 收款来源 | CT1: 客户分组 | CU1: 安装/维修工单号 | CV1: 销售订单号(核销) | CW1: 凭小票 | CX1: 复核日期 | CY1: 复核状态 | CZ1: 复核人 | DA1: 核对标识 | DB1: 师傅姓名 | DC1: 已转账金额 | DD1: 转账状态 | DE1: 费用承担部门 | DF1: 公司承担减免金额 | DG1: AO承担减免金额 | DH1: 费用项目 | DI1: 商场对账单号 | DJ1: 采暖合同编号 | DK1: 用户姓名(单据头) | DL1: 用户手机(单据头) | DM1: 其他号码(单据头) | DN1: 门店承担费用 | DO1: 费用承担门店（非挂账) | DP1: 费用承担员工(非挂账) | DQ1: 员工承担费用 | DR1: 结算人员备注
A2: 现款现货收款单 | B2: SKD250930106 | C2: 杭州 | D2: 2025/10/9 | E2: 客户 | F2: 客户 | G2: 人民币 | H2: 2855.15 | I2: 2838.02 | J2: 杭州中冠电器有限公司 | L2: 杭州中冠电器有限公司 | M2: 杭州红星美凯龙一号店 | N2: 杭州大区 | P2: 2855.15 | Q2: 吴红玉 | R2: 人民币 | S2: 固定汇率 | T2: 1 | U2: 2855.15 | V2: 2838.02 | X2: 完全 | Z2: 销售业务 | AA2: 信用正常 | AB2: 转账 | AC2: 预收款 | AD2: 销售订单 | AE2: 1 | AF2: A20250920001308C | AG2: 2855.15 | AI2: 2855.15 | AJ2: 2855.15 | AK2: 17.13 | AM2: 2838.02 | AN2: 杭州中冠电器有限公司 | AO2: 否 | AP2: 中信银行杭州钱江支行 | AQ2: 手工新增 | AS2: 杭州红星美凯龙一号店 | AX2: 2855.15 | AY2: 否 | AZ2: 7331710182200026317 | BA2: 2855.15 | BC2: 否 | BD2: 2855.15 | BE2: 完全 | BF2: 2855.15 | BG2: 17.13 | BH2: 2838.02 | BI2: 已审核 | BJ2: 陈联 | BK2: 桑玲 | BL2: 桑玲 | BM2: 2025/9/30 | BN2: 2025-10-17 09:18:50 | BO2: 2025-09-30 12:53:56 | BR2: 否 | BS2: 2855.15 | BW2: 杭州中冠电器有限公司 | BX2: 2855.15 | BZ2: 人民币 | CA2: 否 | CB2: 2025/10/9 | CC2: 是 | CD2: RQRS.00006 | CE2: JSQ31-CLD燃气快速热水器 | CF2: A20250920001308C | CG2: 1 | CH2: 否 | CK2: 9.30刷卡3359元（2855.15+补贴503.85元）【用户姓名:廖永芳；用户手机:13777883190；其他号码: 】 | CL2: 2855.15 | CN2: 人民币 | CO2: 固定汇率 | CT2: 杭州地区客户 | CW2: 否 | DD2: 未关闭 | DK2: 廖永芳 | DL2: 13777883190
A3: 现款现货收款单 | B3: SKD250930107 | C3: 杭州 | D3: 2025/10/9 | E3: 客户 | F3: 客户 | G3: 人民币 | H3: 503.85 | I3: 503.85 | J3: 杭州中冠电器有限公司 | L3: 杭州中冠电器有限公司 | M3: 杭州红星美凯龙一号店 | N3: 杭州大区 | P3: 503.85 | Q3: 吴红玉 | R3: 人民币 | S3: 固定汇率 | T3: 1 | U3: 503.85 | V3: 503.85 | X3: 完全 | Z3: 销售业务 | AA3: 信用正常 | AB3: 转账 | AC3: 预收款 | AD3: 销售订单 | AE3: 1 | AF3: A20250920001308C | AG3: 503.85 | AI3: 503.85 | AJ3: 503.85 | AM3: 503.85 | AN3: 政府以旧换新中转银行 | AO3: 否 | AP3: 政府以旧换新中转银行 | AQ3: 手工新增 | AS3: 杭州红星美凯龙一号店 | AX3: 503.85 | AY3: 否 | AZ3: 9999999 | BA3: 503.85 | BC3: 否 | BD3: 503.85 | BE3: 完全 | BF3: 503.85 | BH3: 503.85 | BI3: 已审核 | BJ3: 陈联 | BK3: 陈联 | BL3: 桑玲 | BM3: 2025/9/30 | BN3: 2025-09-30 11:31:23 | BO3: 2025-09-30 12:54:11 | BR3: 否 | BS3: 503.85 | BW3: 杭州中冠电器有限公司 | BX3: 503.85 | BZ3: 人民币 | CA3: 否 | CB3: 2025/10/9 | CC3: 是 | CD3: RQRS.00006 | CE3: JSQ31-CLD燃气快速热水器 | CF3: A20250920001308C | CG3: 1 | CH3: 否 | CK3: 9.30刷卡3359元（2855.15+补贴503.85元）【用户姓名:廖永芳；用户手机:13777883190；其他号码: 】 | CL3: 503.85 | CN3: 人民币 | CO3: 固定汇率 | CT3: 杭州地区客户 | CW3: 否 | DD3: 未关闭 | DK3: 廖永芳 | DL3: 13777883190
A4: 现款现货收款单 | B4: SKD250930109 | C4: 杭州 | D4: 2025/10/9 | E4: 客户 | F4: 客户 | G4: 人民币 | H4: 2623.2 | I4: 2607.46 | J4: 杭州中冠电器有限公司 | L4: 杭州中冠电器有限公司 | M4: 滨江六空8090店 | N4: 杭州大区 | P4: 2623.2 | R4: 人民币 | S4: 固定汇率 | T4: 1 | U4: 2623.2 | V4: 2607.46 | X4: 完全 | Z4: 销售业务 | AA4: 信用正常 | AB4: 转账 | AC4: 预收款 | AD4: 销售订单 | AE4: 1 | AF4: A20250930000866 | AG4: 2623.2 | AI4: 2623.2 | AJ4: 2623.2 | AK4: 15.74 | AM4: 2607.46 | AN4: 杭州中冠电器有限公司 | AO4: 否 | AP4: 中信银行杭州钱江支行 | AQ4: 手工新增 | AS4: 滨江六空8090店 | AX4: 2623.2 | AY4: 否 | AZ4: 7331710182200026317 | BA4: 2623.2 | BC4: 否 | BD4: 2623.2 | BE4: 完全 | BF4: 2623.2 | BG4: 15.74 | BH4: 2607.46 | BI4: 已审核 | BJ4: 葛 芬 | BK4: 桑玲 | BL4: 桑玲 | BM4: 2025/9/30 | BN4: 2025-10-17 09:19:21 | BO4: 2025-09-30 12:56:06 | BR4: 否 | BS4: 2623.2 | BW4: 杭州中冠电器有限公司 | BX4: 2623.2 | BZ4: 人民币 | CA4: 否 | CB4: 2025/10/9 | CC4: 是 | CD4: DRSQ.00060 | CE4: CEWH-60D5Wi储水式热水器 | CF4: A20250930000866 | CG4: 1 | CH4: 否 | CK4: 9.30刷卡3279元（2623.2元+补贴655.8元）【用户姓名：吴璐瑶】【用户姓名:吴璐瑶；用户手机:18757218931；其他号码: 】 | CL4: 2623.2 | CN4: 人民币 | CO4: 固定汇率 | CT4: 杭州-主城 | CW4: 否 | DD4: 未关闭 | DK4: 吴璐瑶 | DL4: 18757218931
A5: 现款现货收款单 | B5: SKD250930111 | C5: 杭州 | D5: 2025/10/9 | E5: 客户 | F5: 客户 | G5: 人民币 | H5: 655.8 | I5: 655.8 | J5: 杭州中冠电器有限公司 | L5: 杭州中冠电器有限公司 | M5: 滨江六空8090店 | N5: 杭州大区 | P5: 655.8 | Q5: 葛芬 | R5: 人民币 | S5: 固定汇率 | T5: 1 | U5: 655.8 | V5: 655.8 | X5: 完全 | Z5: 销售业务 | AA5: 信用正常 | AB5: 转账 | AC5: 预收款 | AD5: 销售订单 | AE5: 1 | AF5: A20250930000866 | AG5: 655.8 | AI5: 655.8 | AJ5: 655.8 | AM5: 655.8 | AN5: 政府以旧换新中转银行 | AO5: 否 | AP5: 政府以旧换新中转银行 | AQ5: 手工新增 | AS5: 滨江六空8090店 | AX5: 655.8 | AY5: 否 | AZ5: 9999999 | BA5: 655.8 | BC5: 否 | BD5: 655.8 | BE5: 完全 | BF5: 655.8 | BH5: 655.8 | BI5: 已审核 | BJ5: 葛 芬 | BK5: 葛 芬 | BL5: 桑玲 | BM5: 2025/9/30 | BN5: 2025-09-30 11:01:08 | BO5: 2025-09-30 12:56:35 | BR5: 否 | BS5: 655.8 | BW5: 杭州中冠电器有限公司 | BX5: 655.8 | BZ5: 人民币 | CA5: 否 | CB5: 2025/10/9 | CC5: 是 | CD5: DRSQ.00060 | CE5: CEWH-60D5Wi储水式热水器 | CF5: A20250930000866 | CG5: 1 | CH5: 否 | CK5: 9.30刷卡3279元（2623.2元+补贴655.8元）【用户姓名：吴璐瑶】【用户姓名:吴璐瑶；用户手机:18757218931；其他号码: 】 | CL5: 655.8 | CN5: 人民币 | CO5: 固定汇率 | CT5: 杭州-主城 | CW5: 否 | DD5: 未关闭 | DK5: 吴璐瑶 | DL5: 18757218931
A6: 现款现货收款单 | B6: SKD250930134 | C6: 杭州 | D6: 2025/10/9 | E6: 客户 | F6: 客户 | G6: 人民币 | H6: 4799.2 | I6: 4770.4 | J6: 杭州中冠电器有限公司 | L6: 杭州中冠电器有限公司 | M6: 滨江六空8090店 | N6: 杭州大区 | P6: 4799.2 | Q6: 葛芬 | R6: 人民币 | S6: 固定汇率 | T6: 1 | U6: 4799.2 | V6: 4770.4 | X6: 完全 | Z6: 销售业务 | AA6: 信用正常 | AB6: 转账 | AC6: 预收款 | AD6: 销售订单 | AE6: 1 | AF6: A20250930000811 | AG6: 4799.2 | AI6: 4799.2 | AJ6: 4799.2 | AK6: 28.8 | AM6: 4770.4 | AN6: 杭州中冠电器有限公司 | AO6: 否 | AP6: 中信银行杭州钱江支行 | AQ6: 手工新增 | AS6: 滨江六空8090店 | AX6: 4799.2 | AY6: 否 | AZ6: 7331710182200026317 | BA6: 4799.2 | BC6: 否 | BD6: 4799.2 | BE6: 完全 | BF6: 4799.2 | BG6: 28.8 | BH6: 4770.4 | BI6: 已审核 | BJ6: 葛 芬 | BK6: 桑玲 | BL6: 桑玲 | BM6: 2025/9/30 | BN6: 2025-10-17 09:19:56 | BO6: 2025-09-30 12:57:26 | BR6: 否 | BS6: 4799.2 | BW6: 杭州中冠电器有限公司 | BX6: 4799.2 | BZ6: 人民币 | CA6: 否 | CB6: 2025/10/9 | CC6: 是 | CD6: SXX(G.00003 | CE6: 洗衣机XQG100-XE0WI | CF6: A20250930000811 | CG6: 1 | CH6: 否 | CK6: 9.30刷卡5999元（4799.2元+补贴1199.8元）【用户姓名：田昆明】【用户姓名:田昆明；用户手机:13958183811；其他号码: 】 | CL6: 4799.2 | CN6: 人民币 | CO6: 固定汇率 | CT6: 杭州-主城 | CW6: 否 | DD6: 未关闭 | DK6: 田昆明 | DL6: 13958183811
A7: 现款现货收款单 | B7: SKD250930136 | C7: 杭州 | D7: 2025/10/9 | E7: 客户 | F7: 客户 | G7: 人民币 | H7: 1199.8 | I7: 1199.8 | J7: 杭州中冠电器有限公司 | L7: 杭州中冠电器有限公司 | M7: 滨江六空8090店 | N7: 杭州大区 | P7: 1199.8 | Q7: 葛芬 | R7: 人民币 | S7: 固定汇率 | T7: 1 | U7: 1199.8 | V7: 1199.8 | X7: 完全 | Z7: 销售业务 | AA7: 信用正常 | AB7: 转账 | AC7: 预收款 | AD7: 销售订单 | AE7: 1 | AF7: A20250930000811 | AG7: 1199.8 | AI7: 1199.8 | AJ7: 1199.8 | AM7: 1199.8 | AN7: 政府以旧换新中转银行 | AO7: 否 | AP7: 政府以旧换新中转银行 | AQ7: 手工新增 | AS7: 滨江六空8090店 | AX7: 1199.8 | AY7: 否 | AZ7: 9999999 | BA7: 1199.8 | BC7: 否 | BD7: 1199.8 | BE7: 完全 | BF7: 1199.8 | BH7: 1199.8 | BI7: 已审核 | BJ7: 葛 芬 | BK7: 葛 芬 | BL7: 桑玲 | BM7: 2025/9/30 | BN7: 2025-09-30 11:19:53 | BO7: 2025-09-30 12:57:43 | BR7: 否 | BS7: 1199.8 | BW7: 杭州中冠电器有限公司 | BX7: 1199.8 | BZ7: 人民币 | CA7: 否 | CB7: 2025/10/9 | CC7: 是 | CD7: SXX(G.00003 | CE7: 洗衣机XQG100-XE0WI | CF7: A20250930000811 | CG7: 1 | CH7: 否 | CK7: 9.30刷卡5999元（4799.2元+补贴1199.8元）【用户姓名：田昆明】【用户姓名:田昆明；用户手机:13958183811；其他号码: 】 | CL7: 1199.8 | CN7: 人民币 | CO7: 固定汇率 | CT7: 杭州-主城 | CW7: 否 | DD7: 未关闭 | DK7: 田昆明 | DL7: 13958183811
A8: 现款现货收款单 | B8: SKD250930225 | C8: 杭州 | D8: 2025/10/9 | E8: 客户 | F8: 客户 | G8: 人民币 | H8: 2855.15 | I8: 2838.02 | J8: 杭州中冠电器有限公司 | L8: 杭州中冠电器有限公司 | M8: 杭州红星美凯龙一号店 | N8: 杭州大区 | P8: 2855.15 | Q8: 吴红玉 | R8: 人民币 | S8: 固定汇率 | T8: 1 | U8: 2855.15 | V8: 2838.02 | X8: 完全 | Z8: 销售业务 | AA8: 信用正常 | AB8: 转账 | AC8: 预收款 | AD8: 销售订单 | AE8: 1 | AF8: A20250930003028 | AG8: 2855.15 | AI8: 2855.15 | AJ8: 2855.15 | AK8: 17.13 | AM8: 2838.02 | AN8: 杭州中冠电器有限公司 | AO8: 否 | AP8: 中信银行杭州钱江支行 | AQ8: 手工新增 | AS8: 杭州红星美凯龙一号店 | AX8: 2855.15 | AY8: 否 | AZ8: 7331710182200026317 | BA8: 2855.15 | BC8: 否 | BD8: 2855.15 | BE8: 完全 | BF8: 2855.15 | BG8: 17.13 | BH8: 2838.02 | BI8: 已审核 | BJ8: 陈联 | BK8: 桑玲 | BL8: 桑玲 | BM8: 2025/9/30 | BN8: 2025-10-07 09:43:51 | BO8: 2025-10-07 09:43:52 | BR8: 否 | BS8: 2855.15 | BW8: 杭州中冠电器有限公司 | BX8: 2855.15 | BZ8: 人民币 | CA8: 否 | CB8: 2025/10/9 | CC8: 是 | CD8: RQRS.00006 | CE8: JSQ31-CLD燃气快速热水器 | CF8: A20250930003028 | CG8: 1 | CH8: 否 | CK8: 9.30刷卡3359元（2855.15+补贴503.85元）【用户姓名:王静涵；用户手机:15990178595；其他号码: 】 | CL8: 2855.15 | CN8: 人民币 | CO8: 固定汇率 | CT8: 杭州地区客户 | CW8: 否 | DD8: 未关闭 | DK8: 王静涵 | DL8: 15990178595
A9: 现款现货收款单 | B9: SKD250930227 | C9: 杭州 | D9: 2025/10/9 | E9: 客户 | F9: 客户 | G9: 人民币 | H9: 503.85 | I9: 503.85 | J9: 杭州中冠电器有限公司 | L9: 杭州中冠电器有限公司 | M9: 杭州红星美凯龙一号店 | N9: 杭州大区 | P9: 503.85 | Q9: 吴红玉 | R9: 人民币 | S9: 固定汇率 | T9: 1 | U9: 503.85 | V9: 503.85 | X9: 完全 | Z9: 销售业务 | AA9: 信用正常 | AB9: 转账 | AC9: 预收款 | AD9: 销售订单 | AE9: 1 | AF9: A20250930003028 | AG9: 503.85 | AI9: 503.85 | AJ9: 503.85 | AM9: 503.85 | AN9: 政府以旧换新中转银行 | AO9: 否 | AP9: 政府以旧换新中转银行 | AQ9: 手工新增 | AS9: 杭州红星美凯龙一号店 | AX9: 503.85 | AY9: 否 | AZ9: 9999999 | BA9: 503.85 | BC9: 否 | BD9: 503.85 | BE9: 完全 | BF9: 503.85 | BH9: 503.85 | BI9: 已审核 | BJ9: 陈联 | BK9: 陈联 | BL9: 桑玲 | BM9: 2025/9/30 | BN9: 2025-09-30 15:35:08 | BO9: 2025-10-07 09:44:01 | BR9: 否 | BS9: 503.85 | BW9: 杭州中冠电器有限公司 | BX9: 503.85 | BZ9: 人民币 | CA9: 否 | CB9: 2025/10/9 | CC9: 是 | CD9: RQRS.00006 | CE9: JSQ31-CLD燃气快速热水器 | CF9: A20250930003028 | CG9: 1 | CH9: 否 | CK9: 9.30刷卡3359元（2855.15+补贴503.85元）【用户姓名:王静涵；用户手机:15990178595；其他号码: 】 | CL9: 503.85 | CN9: 人民币 | CO9: 固定汇率 | CT9: 杭州地区客户 | CW9: 否 | DD9: 未关闭 | DK9: 王静涵 | DL9: 15990178595
A10: 销售收款单 | B10: SKD250930231 | C10: 杭州 | D10: 2025/10/1 | E10: 客户 | F10: 客户 | G10: 人民币 | H10: 11406 | I10: 11331.86 | J10: 杭州中冠电器有限公司 | L10: 杭州中冠电器有限公司 | M10: 自营以旧换新特别账户 | N10: 销管部 | P10: 11406 | Q10: 罗清 | R10: 人民币 | S10: 固定汇率 | T10: 1 | U10: 11406 | V10: 11331.86 | X10: 部分 | Z10: 销售业务 | AA10: 信用正常 | AB10: 转账 | AC10: 销售收款 | AE10: 1 | AG10: 2686 | AI10: 11406 | AJ10: 2686 | AK10: 17.46 | AM10: 2668.54 | AN10: 杭州中冠电器有限公司 | AO10: 否 | AP10: 中信银行杭州钱江支行 | AQ10: 手工新增 | AS10: 自营以旧换新特别账户 | AX10: 2686 | AY10: 否 | AZ10: 7331710182200026317 | BA10: 2686 | BB10: 2025年10月林骞结算(换新1） | BC10: 否 | BE10: 完全 | BF10: 2686 | BG10: 17.46 | BH10: 2668.54 | BI10: 已审核 | BJ10: 毛银萍 | BK10: 桑玲 | BL10: 桑玲 | BM10: 2025/9/30 | BN10: 2025-10-07 09:45:20 | BO10: 2025-10-07 09:45:21 | BR10: 否 | BS10: 2686 | BW10: 杭州中冠电器有限公司 | BX10: 2686 | BZ10: 人民币 | CA10: 否 | CB10: 2025/10/1 | CC10: 是 | CH10: 否 | CK10: 2025年10月1日中信银行收款【用户姓名:2025年10月结算(换新1-4）；用户手机: ；其他号码: 】 | CL10: 2686 | CN10: 人民币 | CO10: 固定汇率 | CT10: 杭州-主城 | CW10: 否 | DD10: 未关闭 | DK10: 2025年10月结算(换新1-4） | DR10: 2025年10月结算(换新1-4）
AB11: 转账 | AC11: 销售收款 | AG11: 2574 | AJ11: 2574 | AK11: 16.73 | AM11: 2557.27 | AN11: 杭州中冠电器有限公司 | AP11: 中信银行杭州钱江支行 | AX11: 2574 | AZ11: 7331710182200026317 | BA11: 2574 | BB11: 2025年10月客户结算(换新2） | BC11: 否 | BE11: 空 | BG11: 16.73 | BH11: 2557.27 | BS11: 2574 | CB11: 2025/10/1 | CC11: 是 | DD11: 未关闭
AB12: 转账 | AC12: 销售收款 | AG12: 3460 | AJ12: 3460 | AK12: 22.49 | AM12: 3437.51 | AN12: 杭州中冠电器有限公司 | AP12: 中信银行杭州钱江支行 | AX12: 3460 | AZ12: 7331710182200026317 | BA12: 3460 | BB12: 2025年10月吴际华结算(换新3） | BC12: 否 | BE12: 空 | BG12: 22.49 | BH12: 3437.51 | BS12: 3460 | CB12: 2025/10/1 | CC12: 是 | DD12: 未关闭
AB13: 转账 | AC13: 销售收款 | AG13: 2686 | AJ13: 2686 | AK13: 17.46 | AM13: 2668.54 | AN13: 杭州中冠电器有限公司 | AP13: 中信银行杭州钱江支行 | AX13: 2686 | AZ13: 7331710182200026317 | BA13: 2686 | BB13: 2025年10月钱冰结算(换新4） | BC13: 否 | BE13: 空 | BG13: 17.46 | BH13: 2668.54 | BS13: 2686 | CB13: 2025/10/1 | CC13: 是 | DD13: 未关闭
A14: 现款现货收款单 | B14: SKD251001016 | C14: 杭州 | D14: 2025/10/9 | E14: 客户 | F14: 客户 | G14: 人民币 | H14: 2991.2 | I14: 2973.25 | J14: 杭州中冠电器有限公司 | L14: 杭州中冠电器有限公司 | M14: 滨江六空8090店 | N14: 杭州大区 | P14: 2991.2 | Q14: 葛芬 | R14: 人民币 | S14: 固定汇率 | T14: 1 | U14: 2991.2 | V14: 2973.25 | X14: 完全 | Z14: 销售业务 | AA14: 信用正常 | AB14: 转账 | AC14: 预收款 | AD14: 销售订单 | AE14: 1 | AF14: A20251001004169 | AG14: 2991.2 | AI14: 2991.2 | AJ14: 2991.2 | AK14: 17.95 | AM14: 2973.25 | AN14: 杭州中冠电器有限公司 | AO14: 否 | AP14: 中信银行杭州钱江支行 | AQ14: 手工新增 | AS14: 滨江六空8090店 | AX14: 2991.2 | AY14: 否 | AZ14: 7331710182200026317 | BA14: 2991.2 | BC14: 否 | BD14: 2991.2 | BE14: 完全 | BF14: 2991.2 | BG14: 17.95 | BH14: 2973.25 | BI14: 已审核 | BJ14: 葛 芬 | BK14: 桑玲 | BL14: 桑玲 | BM14: 2025/10/1 | BN14: 2025-10-07 09:23:52 | BO14: 2025-10-02 12:41:01 | BR14: 否 | BS14: 2991.2 | BW14: 杭州中冠电器有限公司 | BX14: 2991.2 | BZ14: 人民币 | CA14: 否 | CB14: 2025/10/9 | CC14: 是 | CD14: DR.00103 | CE14: EWH-60DA储水式电热水器 | CF14: A20251001004169 | CG14: 1 | CH14: 否 | CK14: 10.1刷卡3739元(2991.2元+补贴747.8元）【用户姓名：钱江】【用户姓名:钱江；用户手机:15381018947；其他号码: 】 | CL14: 2991.2 | CN14: 人民币 | CO14: 固定汇率 | CT14: 杭州-主城 | CW14: 否 | DD14: 未关闭 | DK14: 钱江 | DL14: 15381018947
A15: 现款现货收款单 | B15: SKD251001018 | C15: 杭州 | D15: 2025/10/9 | E15: 客户 | F15: 客户 | G15: 人民币 | H15: 747.8 | I15: 747.8 | J15: 杭州中冠电器有限公司 | L15: 杭州中冠电器有限公司 | M15: 滨江六空8090店 | N15: 杭州大区 | P15: 747.8 | Q15: 葛芬 | R15: 人民币 | S15: 固定汇率 | T15: 1 | U15: 747.8 | V15: 747.8 | X15: 完全 | Z15: 销售业务 | AA15: 信用正常 | AB15: 转账 | AC15: 预收款 | AD15: 销售订单 | AE15: 1 | AF15: A20251001004169 | AG15: 747.8 | AI15: 747.8 | AJ15: 747.8 | AM15: 747.8 | AN15: 政府以旧换新中转银行 | AO15: 否 | AP15: 政府以旧换新中转银行 | AQ15: 手工新增 | AS15: 滨江六空8090店 | AX15: 747.8 | AY15: 否 | AZ15: 9999999 | BA15: 747.8 | BC15: 否 | BD15: 747.8 | BE15: 完全 | BF15: 747.8 | BH15: 747.8 | BI15: 已审核 | BJ15: 葛 芬 | BK15: 葛 芬 | BL15: 桑玲 | BM15: 2025/10/1 | BN15: 2025-10-01 13:43:52 | BO15: 2025-10-02 12:41:11 | BR15: 否 | BS15: 747.8 | BW15: 杭州中冠电器有限公司 | BX15: 747.8 | BZ15: 人民币 | CA15: 否 | CB15: 2025/10/9 | CC15: 是 | CD15: DR.00103 | CE15: EWH-60DA储水式电热水器 | CF15: A20251001004169 | CG15: 1 | CH15: 否 | CK15: 10.1刷卡3739元(2991.2元+补贴747.8元）【用户姓名：钱江】【用户姓名:钱江；用户手机:15381018947；其他号码: 】 | CL15: 747.8 | CN15: 人民币 | CO15: 固定汇率 | CT15: 杭州-主城 | CW15: 否 | DD15: 未关闭 | DK15: 钱江 | DL15: 15381018947
A16: 现款现货收款单 | B16: SKD251001020 | C16: 杭州 | D16: 2025/10/9 | E16: 客户 | F16: 客户 | G16: 人民币 | H16: 2240 | I16: 2226.56 | J16: 杭州中冠电器有限公司 | L16: 杭州中冠电器有限公司 | M16: 滨江六空8090店 | N16: 杭州大区 | P16: 2240 | Q16: 葛芬 | R16: 人民币 | S16: 固定汇率 | T16: 1 | U16: 2240 | V16: 2226.56 | X16: 空 | Z16: 销售业务 | AA16: 信用正常 | AB16: 转账 | AC16: 预收款 | AD16: 销售订单 | AE16: 1 | AF16: A20251001004530 | AG16: 2240 | AI16: 2240 | AJ16: 2240 | AK16: 13.44 | AM16: 2226.56 | AN16: 杭州中冠电器有限公司 | AO16: 否 | AP16: 中信银行杭州钱江支行 | AQ16: 手工新增 | AS16: 滨江六空8090店 | AX16: 2240 | AY16: 否 | AZ16: 7331710182200026317 | BA16: 2240 | BC16: 否 | BD16: 2240 | BE16: 空 | BG16: 13.44 | BH16: 2226.56 | BI16: 已审核 | BJ16: 葛 芬 | BK16: 桑玲 | BL16: 桑玲 | BM16: 2025/10/1 | BN16: 2025-10-07 09:24:21 | BO16: 2025-10-02 12:41:22 | BR16: 否 | BS16: 2240 | BW16: 杭州中冠电器有限公司 | BZ16: 人民币 | CA16: 否 | CB16: 2025/10/9 | CC16: 是 | CD16: DRSQ.00070 | CE16: CEWH-60D1BWi储水式热水器 | CF16: A20251001004530 | CG16: 1 | CH16: 否 | CK16: 10.1刷卡2800元(2240元+补贴560元）【用户姓名：洪二香】【用户姓名:洪二香；用户手机:13738157701；其他号码: 】 | CN16: 人民币 | CO16: 固定汇率 | CT16: 杭州-主城 | CW16: 否 | DD16: 未关闭 | DK16: 洪二香 | DL16: 13738157701
A17: 现款现货收款单 | B17: SKD251001021 | C17: 杭州 | D17: 2025/10/9 | E17: 客户 | F17: 客户 | G17: 人民币 | H17: 560 | I17: 560 | J17: 杭州中冠电器有限公司 | L17: 杭州中冠电器有限公司 | M17: 滨江六空8090店 | N17: 杭州大区 | P17: 560 | Q17: 葛芬 | R17: 人民币 | S17: 固定汇率 | T17: 1 | U17: 560 | V17: 560 | X17: 空 | Z17: 销售业务 | AA17: 信用正常 | AB17: 转账 | AC17: 预收款 | AD17: 销售订单 | AE17: 1 | AF17: A20251001004530 | AG17: 560 | AI17: 560 | AJ17: 560 | AM17: 560 | AN17: 政府以旧换新中转银行 | AO17: 否 | AP17: 政府以旧换新中转银行 | AQ17: 手工新增 | AS17: 滨江六空8090店 | AX17: 560 | AY17: 否 | AZ17: 9999999 | BA17: 560 | BC17: 否 | BD17: 560 | BE17: 空 | BH17: 560 | BI17: 已审核 | BJ17: 葛 芬 | BK17: 葛 芬 | BL17: 桑玲 | BM17: 2025/10/1 | BN17: 2025-10-01 14:21:40 | BO17: 2025-10-02 12:41:56 | BR17: 否 | BS17: 560 | BW17: 杭州中冠电器有限公司 | BZ17: 人民币 | CA17: 否 | CB17: 2025/10/9 | CC17: 是 | CD17: DRSQ.00070 | CE17: CEWH-60D1BWi储水式热水器 | CF17: A20251001004530 | CG17: 1 | CH17: 否 | CK17: 10.1刷卡2800元(2240元+补贴560元）【用户姓名：洪二香】【用户姓名:洪二香；用户手机:13738157701；其他号码: 】 | CN17: 人民币 | CO17: 固定汇率 | CT17: 杭州-主城 | CW17: 否 | DD17: 未关闭 | DK17: 洪二香 | DL17: 13738157701
A18: 现款现货收款单 | B18: SKD251002016 | C18: 杭州 | D18: 2025/10/1 | E18: 客户 | F18: 客户 | G18: 人民币 | H18: 4399 | I18: 4399 | J18: 杭州中冠电器有限公司 | L18: 杭州中冠电器有限公司 | M18: 萧山第六空间专卖店 | N18: 杭州大区 | P18: 4399 | Q18: 徐美娟 | R18: 人民币 | S18: 固定汇率 | T18: 1 | U18: 4399 | V18: 4399 | X18: 完全 | Z18: 销售业务 | AA18: 信用正常 | AB18: 转账 | AC18: 预收款 | AD18: 销售订单 | AE18: 1 | AF18: A20251001008995 | AG18: 4399 | AI18: 4399 | AJ18: 4399 | AM18: 4399 | AN18: 杭州中冠电器有限公司支付宝 | AO18: 否 | AP18: 杭州中冠电器有限公司支付宝 | AQ18: 手工新增 | AS18: 萧山第六空间专卖店 | AX18: 4399 | AY18: 否 | AZ18: hzzgcw@163.com | BA18: 4399 | BC18: 否 | BD18: 4399 | BE18: 完全 | BF18: 4399 | BH18: 4399 | BI18: 已审核 | BJ18: 徐美娟 | BK18: 桑玲 | BL18: 桑玲 | BM18: 2025/10/2 | BN18: 2025-10-02 12:43:47 | BO18: 2025-10-02 12:44:05 | BR18: 否 | BS18: 4399 | BW18: 杭州中冠电器有限公司 | BX18: 4399 | BZ18: 人民币 | CA18: 否 | CB18: 2025/10/1 | CC18: 是 | CD18: DRSQ.00026 | CE18: EWH-60HGCWi薄型电热水器 | CF18: A20251001008995 | CG18: 1 | CH18: 否 | CK18: 10.1号王旭支付宝转账4399元【用户姓名:王旭；用户手机:15157146987；其他号码: 】 | CL18: 4399 | CN18: 人民币 | CO18: 固定汇率 | CT18: 杭州-萧山 | CW18: 否 | DD18: 未关闭 | DK18: 王旭 | DL18: 15157146987 | DR18: 2025100122001464461405582215
A19: 现款现货收款单 | B19: SKD251002032 | C19: 金华 | D19: 2025/10/2 | E19: 客户 | F19: 客户 | G19: 人民币 | H19: 4059 | I19: 4050.27 | J19: 杭州中冠电器有限公司 | L19: 杭州中冠电器有限公司 | M19: 金华龙腾建材市场专卖店 | N19: 金华办事处 | P19: 4059 | Q19: 潘杏 | R19: 人民币 | S19: 固定汇率 | T19: 1 | U19: 4059 | V19: 4050.27 | X19: 完全 | Z19: 销售业务 | AA19: 信用正常 | AB19: 扫码牌 | AC19: 预收款 | AD19: 销售订单 | AE19: 1 | AF19: A20251001006320 | AG19: 4059 | AI19: 4059 | AJ19: 4059 | AK19: 8.73 | AM19: 4050.27 | AN19: 杭州中冠电器有限公司 | AO19: 否 | AP19: 中信银行杭州钱江支行 | AQ19: 手工新增 | AS19: 金华龙腾建材市场专卖店 | AX19: 4059 | AY19: 否 | AZ19: 7331710182200026317 | BA19: 4059 | BC19: 否 | BD19: 4059 | BE19: 完全 | BF19: 4059 | BG19: 8.73 | BH19: 4050.27 | BI19: 已审核 | BJ19: 周琴 | BK19: 桑玲 | BL19: 桑玲 | BM19: 2025/10/2 | BN19: 2025-10-02 12:47:37 | BO19: 2025-10-02 12:48:11 | BR19: 否 | BS19: 4059 | BW19: 杭州中冠电器有限公司 | BX19: 4059 | BZ19: 人民币 | CA19: 否 | CB19: 2025/10/2 | CC19: 是 | CD19: RQRS.00050 | CE19: JSW31-VOSWi燃气热水器（含排烟组件总成403879-079） | CF19: A20251001006320 | CG19: 1 | CH19: 否 | CK19: 10.1号扫码支付4059【用户姓名:诸葛伟；用户手机:15258992858；其他号码: 】 | CL19: 4059 | CN19: 人民币 | CO19: 固定汇率 | CT19: 金华-主城 | CW19: 否 | DD19: 未关闭 | DK19: 诸葛伟 | DL19: 15258992858
A20: 现款现货收款单 | B20: SKD251002033 | C20: 金华 | D20: 2025/10/3 | E20: 客户 | F20: 客户 | G20: 人民币 | H20: 3599 | I20: 3591.26 | J20: 杭州中冠电器有限公司 | L20: 杭州中冠电器有限公司 | M20: 金华龙腾建材市场专卖店 | N20: 金华办事处 | P20: 3599 | Q20: 潘杏 | R20: 人民币 | S20: 固定汇率 | T20: 1 | U20: 3599 | V20: 3591.26 | X20: 完全 | Z20: 销售业务 | AA20: 信用正常 | AB20: 扫码牌 | AC20: 预收款 | AD20: 销售订单 | AE20: 1 | AF20: A20251002000780 | AG20: 3599 | AI20: 3599 | AJ20: 3599 | AK20: 7.74 | AM20: 3591.26 | AN20: 杭州中冠电器有限公司 | AO20: 否 | AP20: 中信银行杭州钱江支行 | AQ20: 手工新增 | AS20: 金华龙腾建材市场专卖店 | AX20: 3599 | AY20: 否 | AZ20: 7331710182200026317 | BA20: 3599 | BC20: 否 | BD20: 3599 | BE20: 完全 | BF20: 3599 | BG20: 7.74 | BH20: 3591.26 | BI20: 已审核 | BJ20: 周琴 | BK20: 桑玲 | BL20: 桑玲 | BM20: 2025/10/2 | BN20: 2025-10-07 09:25:24 | BO20: 2025-10-03 14:57:42 | BR20: 否 | BS20: 3599 | BW20: 杭州中冠电器有限公司 | BX20: 3599 | BZ20: 人民币 | CA20: 否 | CB20: 2025/10/3 | CC20: 是 | CD20: DRSQ.00039 | CE20: CEWH-100KWi电热水器 | CF20: A20251002000780 | CG20: 1 | CH20: 否 | CK20: 10.2扫码支付3599【用户姓名:林爱花；用户手机:13857981322；其他号码: 】 | CL20: 3599 | CN20: 人民币 | CO20: 固定汇率 | CT20: 金华-主城 | CW20: 否 | DD20: 未关闭 | DK20: 林爱花 | DL20: 13857981322
A21: 销售收款单 | B21: SKD251002034 | C21: 金华 | D21: 2025/10/2 | E21: 客户 | F21: 客户 | G21: 人民币 | H21: 2360 | I21: 2360 | J21: 杭州中冠电器有限公司 | L21: 杭州中冠电器有限公司 | M21: 衢州市柯城汇鑫家用电器商行 | N21: 金华办事处 | P21: 2360 | Q21: 江雯 | R21: 人民币 | S21: 固定汇率 | T21: 1 | U21: 2360 | V21: 2360 | X21: 空 | Z21: 销售业务 | AA21: 信用正常 | AB21: 转账 | AC21: 销售收款 | AE21: 1 | AG21: 2360 | AI21: 2360 | AJ21: 2360 | AM21: 2360 | AN21: 李扬-金华 | AO21: 否 | AP21: 中国建设银行股份有限公司金华经济开发区支行 | AQ21: 手工新增 | AS21: 衢州市柯城汇鑫家用电器商行 | AX21: 2360 | AY21: 否 | AZ21: 4367421460407338728 | BA21: 2360 | BC21: 否 | BE21: 空 | BH21: 2360 | BI21: 已审核 | BJ21: 王小婷 | BK21: 王小婷 | BL21: 桑玲 | BM21: 2025/10/2 | BN21: 2025-10-02 13:04:23 | BO21: 2025-10-03 14:55:29 | BR21: 否 | BS21: 2360 | BW21: 杭州中冠电器有限公司 | BZ21: 人民币 | CA21: 否 | CB21: 2025/10/2 | CC21: 是 | CH21: 否 | CK21: 10.2金华建行2360【用户姓名:郑星；用户手机: ；其他号码: 】 | CN21: 人民币 | CO21: 固定汇率 | CT21: 衢州-主城 | CW21: 否 | DD21: 未关闭 | DK21: 郑星
A22: 现款现货收款单 | B22: SKD251002077 | C22: 杭州 | D22: 2025/10/2 | E22: 客户 | F22: 客户 | G22: 人民币 | H22: 2071 | I22: 2071 | J22: 杭州中冠电器有限公司 | L22: 杭州中冠电器有限公司 | M22: 杭州红星美凯龙一号店 | N22: 杭州大区 | P22: 2071 | Q22: 吴红玉 | R22: 人民币 | S22: 固定汇率 | T22: 1 | U22: 2071 | V22: 2071 | X22: 完全 | Z22: 销售业务 | AA22: 信用正常 | AB22: 转账 | AC22: 预收款 | AD22: 销售订单 | AE22: 1 | AF22: A20251002000984 | AG22: 2071 | AI22: 2071 | AJ22: 2071 | AM22: 2071 | AN22: 杭州中冠电器有限公司支付宝 | AO22: 否 | AP22: 杭州中冠电器有限公司支付宝 | AQ22: 手工新增 | AS22: 杭州红星美凯龙一号店 | AX22: 2071 | AY22: 否 | AZ22: hzzgcw@163.com | BA22: 2071 | BC22: 否 | BD22: 2071 | BE22: 完全 | BF22: 2071 | BH22: 2071 | BI22: 已审核 | BJ22: 陈联 | BK22: 陈联 | BL22: 桑玲 | BM22: 2025/10/2 | BN22: 2025-10-02 15:09:04 | BO22: 2025-10-03 14:49:21 | BR22: 否 | BS22: 2071 | BW22: 杭州中冠电器有限公司 | BX22: 2071 | BZ22: 人民币 | CA22: 否 | CB22: 2025/10/2 | CC22: 是 | CD22: YSJ.00056 | CE22: APM-HC1 管线机 | CF22: A20251002000984 | CG22: 1 | CH22: 否 | CK22: 10.2支付宝2071元【用户姓名:张艳佳；用户手机:18357002327；其他号码: 】 | CL22: 2071 | CN22: 人民币 | CO22: 固定汇率 | CT22: 杭州地区客户 | CW22: 否 | DD22: 未关闭 | DK22: 张艳佳 | DL22: 18357002327 | DR22: '2025100222001400021430908377
A23: 现款现货收款单 | B23: SKD251002078 | C23: 杭州 | D23: 2025/10/2 | E23: 客户 | F23: 客户 | G23: 人民币 | H23: 3439 | I23: 3439 | J23: 杭州中冠电器有限公司 | L23: 杭州中冠电器有限公司 | M23: 杭州红星美凯龙一号店 | N23: 杭州大区 | P23: 3439 | Q23: 吴红玉 | R23: 人民币 | S23: 固定汇率 | T23: 1 | U23: 3439 | V23: 3439 | X23: 完全 | Z23: 销售业务 | AA23: 信用正常 | AB23: 转账 | AC23: 预收款 | AD23: 销售订单 | AE23: 1 | AF23: A20251002002898 | AG23: 3439 | AI23: 3439 | AJ23: 3439 | AM23: 3439 | AN23: 杭州中冠电器有限公司支付宝 | AO23: 否 | AP23: 杭州中冠电器有限公司支付宝 | AQ23: 手工新增 | AS23: 杭州红星美凯龙一号店 | AX23: 3439 | AY23: 否 | AZ23: hzzgcw@163.com | BA23: 3439 | BC23: 否 | BD23: 3439 | BE23: 完全 | BF23: 3439 | BH23: 3439 | BI23: 已审核 | BJ23: 陈联 | BK23: 陈联 | BL23: 桑玲 | BM23: 2025/10/2 | BN23: 2025-10-03 10:33:47 | BO23: 2025-10-03 14:49:04 | BR23: 否 | BS23: 3439 | BW23: 杭州中冠电器有限公司 | BX23: 3439 | BZ23: 人民币 | CA23: 否 | CB23: 2025/10/2 | CC23: 是 | CD23: DR.00103 | CE23: EWH-60DA储水式电热水器 | CF23: A20251002002898 | CG23: 1 | CH23: 否 | CK23: 10.2支付宝3439元【用户姓名:吴苏萍；用户手机:13666640691；其他号码: 】 | CL23: 3439 | CN23: 人民币 | CO23: 固定汇率 | CT23: 杭州地区客户 | CW23: 否 | DD23: 未关闭 | DK23: 吴苏萍 | DL23: 13666640691 | DR23: 2025100222001431571449156527
A24: 销售收款单 | B24: SKD251003058 | C24: 杭州 | D24: 2025/10/3 | E24: 客户 | F24: 客户 | G24: 人民币 | H24: 3439 | I24: 3431.61 | J24: 杭州中冠电器有限公司 | L24: 杭州中冠电器有限公司 | M24: 杭州红星美凯龙一号店 | N24: 杭州大区 | P24: 3439 | Q24: 吴红玉 | R24: 人民币 | S24: 固定汇率 | T24: 1 | U24: 3439 | V24: 3431.61 | X24: 完全 | Z24: 销售业务 | AA24: 信用正常 | AB24: 扫码牌 | AC24: 销售收款 | AE24: 1 | AG24: 3439 | AI24: 3439 | AJ24: 3439 | AK24: 7.39 | AM24: 3431.61 | AN24: 杭州中冠电器有限公司 | AO24: 否 | AP24: 中信银行杭州钱江支行 | AQ24: 手工新增 | AS24: 杭州红星美凯龙一号店 | AX24: 3439 | AY24: 否 | AZ24: 7331710182200026317 | BA24: 3439 | BC24: 否 | BE24: 完全 | BF24: 3439 | BG24: 7.39 | BH24: 3431.61 | BI24: 已审核 | BJ24: 陈联 | BK24: 桑玲 | BL24: 桑玲 | BM24: 2025/10/3 | BN24: 2025-10-07 09:46:14 | BO24: 2025-10-07 09:46:14 | BR24: 否 | BS24: 3439 | BW24: 杭州中冠电器有限公司 | BX24: 3439 | BZ24: 人民币 | CA24: 否 | CB24: 2025/10/3 | CC24: 是 | CH24: 否 | CK24: 10.2扫码付3439元【用户姓名:吴苏萍；用户手机:13666640691；其他号码: 】 | CL24: 3439 | CN24: 人民币 | CO24: 固定汇率 | CT24: 杭州地区客户 | CW24: 否 | DD24: 未关闭 | DK24: 吴苏萍 | DL24: 13666640691
A25: 现款现货收款单 | B25: SKD251003063 | C25: 杭州 | D25: 2025/10/2 | E25: 客户 | F25: 客户 | G25: 人民币 | H25: 5220 | I25: 5220 | J25: 杭州中冠电器有限公司 | L25: 杭州中冠电器有限公司 | M25: 杭州红星美凯龙一号店 | N25: 杭州大区 | P25: 5220 | Q25: 吴红玉 | R25: 人民币 | S25: 固定汇率 | T25: 1 | U25: 5220 | V25: 5220 | X25: 完全 | Z25: 销售业务 | AA25: 信用正常 | AB25: 转账 | AC25: 预收款 | AD25: 销售订单 | AE25: 1 | AF25: A20251003000652 | AG25: 5220 | AI25: 5220 | AJ25: 5220 | AM25: 5220 | AN25: 杭州中冠电器有限公司支付宝 | AO25: 否 | AP25: 杭州中冠电器有限公司支付宝 | AQ25: 手工新增 | AS25: 杭州红星美凯龙一号店 | AX25: 5220 | AY25: 否 | AZ25: hzzgcw@163.com | BA25: 5220 | BC25: 否 | BD25: 5220 | BE25: 完全 | BF25: 5220 | BH25: 5220 | BI25: 已审核 | BJ25: 陈联 | BK25: 陈联 | BL25: 桑玲 | BM25: 2025/10/3 | BN25: 2025-10-03 10:38:21 | BO25: 2025-10-03 14:48:41 | BR25: 否 | BS25: 5220 | BW25: 杭州中冠电器有限公司 | BX25: 5220 | BZ25: 人民币 | CA25: 否 | CB25: 2025/10/2 | CC25: 是 | CD25: DRSQ.00027 | CE25: EWH-80HGCWi薄型电热水器 | CF25: A20251003000652 | CG25: 1 | CH25: 否 | CK25: 10.2支付宝5220元【用户姓名:郑笑平；用户手机:13575840935；其他号码: 】 | CL25: 5220 | CN25: 人民币 | CO25: 固定汇率 | CT25: 杭州地区客户 | CW25: 否 | DD25: 未关闭 | DK25: 郑笑平 | DL25: 13575840935 | DR25: '2025100222001431511430156610
A26: 现款现货收款单 | B26: SKD251003091 | C26: 杭州 | D26: 2025/10/9 | E26: 客户 | F26: 客户 | G26: 人民币 | H26: 2460.8 | I26: 2446.04 | J26: 杭州中冠电器有限公司 | L26: 杭州中冠电器有限公司 | M26: 杭州红星美凯龙一号店 | N26: 杭州大区 | P26: 2460.8 | Q26: 吴红玉 | R26: 人民币 | S26: 固定汇率 | T26: 1 | U26: 2460.8 | V26: 2446.04 | X26: 完全 | Z26: 销售业务 | AA26: 信用正常 | AB26: 转账 | AC26: 预收款 | AD26: 销售订单 | AE26: 1 | AF26: A20250919005149C | AG26: 2460.8 | AI26: 2460.8 | AJ26: 2460.8 | AK26: 14.76 | AM26: 2446.04 | AN26: 杭州中冠电器有限公司 | AO26: 否 | AP26: 中信银行杭州钱江支行 | AQ26: 手工新增 | AS26: 杭州红星美凯龙一号店 | AX26: 2460.8 | AY26: 否 | AZ26: 7331710182200026317 | BA26: 2460.8 | BC26: 否 | BD26: 2460.8 | BE26: 完全 | BF26: 2460.8 | BG26: 14.76 | BH26: 2446.04 | BI26: 已审核 | BJ26: 陈联 | BK26: 桑玲 | BL26: 桑玲 | BM26: 2025/10/3 | BN26: 2025-10-07 09:26:43 | BO26: 2025-10-03 14:50:55 | BR26: 否 | BS26: 2460.8 | BW26: 杭州中冠电器有限公司 | BX26: 2460.8 | BZ26: 人民币 | CA26: 否 | CB26: 2025/10/9 | CC26: 是 | CD26: DRSQ.00067 | CE26: CEWH-60D1Wi储水电热水器 | CF26: A20250919005149C | CG26: 1 | CH26: 否 | CK26: 10.1刷卡3076元（2460.8+补贴615.20元）【用户姓名:李冬梅；用户手机:13705719928；其他号码: 】 | CL26: 2460.8 | CN26: 人民币 | CO26: 固定汇率 | CT26: 杭州地区客户 | CW26: 否 | DD26: 未关闭 | DK26: 李冬梅 | DL26: 13705719928
A27: 现款现货收款单 | B27: SKD251003092 | C27: 杭州 | D27: 2025/10/9 | E27: 客户 | F27: 客户 | G27: 人民币 | H27: 615.2 | I27: 615.2 | J27: 杭州中冠电器有限公司 | L27: 杭州中冠电器有限公司 | M27: 杭州红星美凯龙一号店 | N27: 杭州大区 | P27: 615.2 | Q27: 吴红玉 | R27: 人民币 | S27: 固定汇率 | T27: 1 | U27: 615.2 | V27: 615.2 | X27: 完全 | Z27: 销售业务 | AA27: 信用正常 | AB27: 转账 | AC27: 预收款 | AD27: 销售订单 | AE27: 1 | AF27: A20250919005149C | AG27: 615.2 | AI27: 615.2 | AJ27: 615.2 | AM27: 615.2 | AN27: 政府以旧换新中转银行 | AO27: 否 | AP27: 政府以旧换新中转银行 | AQ27: 手工新增 | AS27: 杭州红星美凯龙一号店 | AX27: 615.2 | AY27: 否 | AZ27: 9999999 | BA27: 615.2 | BC27: 否 | BD27: 615.2 | BE27: 完全 | BF27: 615.2 | BH27: 615.2 | BI27: 已审核 | BJ27: 陈联 | BK27: 陈联 | BL27: 桑玲 | BM27: 2025/10/3 | BN27: 2025-10-03 11:00:29 | BO27: 2025-10-03 14:51:18 | BR27: 否 | BS27: 615.2 | BW27: 杭州中冠电器有限公司 | BX27: 615.2 | BZ27: 人民币 | CA27: 否 | CB27: 2025/10/9 | CC27: 是 | CD27: DRSQ.00067 | CE27: CEWH-60D1Wi储水电热水器 | CF27: A20250919005149C | CG27: 1 | CH27: 否 | CK27: 10.1刷卡3076元（2460.8+补贴615.20元）【用户姓名:李冬梅；用户手机:13705719928；其他号码: 】 | CL27: 615.2 | CN27: 人民币 | CO27: 固定汇率 | CT27: 杭州地区客户 | CW27: 否 | DD27: 未关闭 | DK27: 李冬梅 | DL27: 13705719928
A28: 现款现货收款单 | B28: SKD251003135 | C28: 杭州 | D28: 2025/10/3 | E28: 客户 | F28: 客户 | G28: 人民币 | H28: 3639 | I28: 3639 | J28: 杭州中冠电器有限公司 | L28: 杭州中冠电器有限公司 | M28: 滨江六空8090店 | N28: 杭州大区 | P28: 3639 | Q28: 葛芬 | R28: 人民币 | S28: 固定汇率 | T28: 1 | U28: 3639 | V28: 3639 | X28: 完全 | Z28: 销售业务 | AA28: 信用正常 | AB28: 转账 | AC28: 预收款 | AD28: 销售订单 | AE28: 1 | AF28: A20251003001834 | AG28: 3639 | AI28: 3639 | AJ28: 3639 | AM28: 3639 | AN28: 杭州中冠电器有限公司支付宝 | AO28: 否 | AP28: 杭州中冠电器有限公司支付宝 | AQ28: 手工新增 | AS28: 滨江六空8090店 | AX28: 3639 | AY28: 否 | AZ28: hzzgcw@163.com | BA28: 3639 | BC28: 否 | BD28: 3639 | BE28: 完全 | BF28: 3639 | BH28: 3639 | BI28: 已审核 | BJ28: 葛 芬 | BK28: 桑玲 | BL28: 桑玲 | BM28: 2025/10/3 | BN28: 2025-10-07 09:28:05 | BO28: 2025-10-07 09:28:06 | BR28: 否 | BS28: 3639 | BW28: 杭州中冠电器有限公司 | BX28: 3639 | BZ28: 人民币 | CA28: 否 | CB28: 2025/10/3 | CC28: 是 | CD28: DR.00103 | CE28: EWH-60DA储水式电热水器 | CF28: A20251003001834 | CG28: 1 | CH28: 否 | CK28: 10.3支付宝转账3639元（用户名 王旭东）【用户姓名:王旭东；用户手机:13750837396；其他号码: 】 | CL28: 3639 | CN28: 人民币 | CO28: 固定汇率 | CT28: 杭州-主城 | CW28: 否 | DD28: 未关闭 | DK28: 王旭东 | DL28: 13750837396 | DR28: 2025100322001459741433588445
A29: 现款现货收款单 | B29: SKD251003136 | C29: 杭州 | D29: 2025/10/3 | E29: 客户 | F29: 客户 | G29: 人民币 | H29: 2591 | I29: 2591 | J29: 杭州中冠电器有限公司 | L29: 杭州中冠电器有限公司 | M29: 杭州红星美凯龙一号店 | N29: 杭州大区 | P29: 2591 | Q29: 吴红玉 | R29: 人民币 | S29: 固定汇率 | T29: 1 | U29: 2591 | V29: 2591 | X29: 完全 | Z29: 销售业务 | AA29: 信用正常 | AB29: 转账 | AC29: 预收款 | AD29: 销售订单 | AE29: 1 | AF29: A20251003000910 | AG29: 2591 | AI29: 2591 | AJ29: 2591 | AM29: 2591 | AN29: 杭州中冠电器有限公司支付宝 | AO29: 否 | AP29: 杭州中冠电器有限公司支付宝 | AQ29: 手工新增 | AS29: 杭州红星美凯龙一号店 | AX29: 2591 | AY29: 否 | AZ29: hzzgcw@163.com | BA29: 2591 | BC29: 否 | BD29: 2591 | BE29: 完全 | BF29: 2591 | BH29: 2591 | BI29: 已审核 | BJ29: 陈联 | BK29: 陈联 | BL29: 桑玲 | BM29: 2025/10/3 | BN29: 2025-10-03 13:21:40 | BO29: 2025-10-03 14:45:23 | BR29: 否 | BS29: 2591 | BW29: 杭州中冠电器有限公司 | BX29: 2591 | BZ29: 人民币 | CA29: 否 | CB29: 2025/10/3 | CC29: 是 | CD29: DRSQ.00070 | CE29: CEWH-60D1BWi储水式热水器 | CF29: A20251003000910 | CG29: 1 | CH29: 否 | CK29: 10.3支付宝2591元【用户姓名:金丽敏；用户手机:13335710581；其他号码: 】 | CL29: 2591 | CN29: 人民币 | CO29: 固定汇率 | CT29: 杭州地区客户 | CW29: 否 | DD29: 未关闭 | DK29: 金丽敏 | DL29: 13335710581 | DR29: '2025100322001453241419896070
A30: 现款现货收款单 | B30: SKD251003149 | C30: 杭州 | D30: 2025/10/9 | E30: 客户 | F30: 客户 | G30: 人民币 | H30: 2908.8 | I30: 2891.35 | J30: 杭州中冠电器有限公司 | L30: 杭州中冠电器有限公司 | M30: 杭州红星美凯龙一号店 | N30: 杭州大区 | P30: 2908.8 | Q30: 吴红玉 | R30: 人民币 | S30: 固定汇率 | T30: 1 | U30: 2908.8 | V30: 2891.35 | X30: 完全 | Z30: 销售业务 | AA30: 信用正常 | AB30: 转账 | AC30: 预收款 | AD30: 销售订单 | AE30: 1 | AF30: A20251002000983 | AG30: 2908.8 | AI30: 2908.8 | AJ30: 2908.8 | AK30: 17.45 | AM30: 2891.35 | AN30: 杭州中冠电器有限公司 | AO30: 否 | AP30: 中信银行杭州钱江支行 | AQ30: 手工新增 | AS30: 杭州红星美凯龙一号店 | AX30: 2908.8 | AY30: 否 | AZ30: 7331710182200026317 | BA30: 2908.8 | BC30: 否 | BD30: 2908.8 | BE30: 完全 | BF30: 2908.8 | BG30: 17.45 | BH30: 2891.35 | BI30: 已审核 | BJ30: 陈联 | BK30: 桑玲 | BL30: 桑玲 | BM30: 2025/10/3 | BN30: 2025-10-07 09:35:42 | BO30: 2025-10-06 14:23:59 | BR30: 否 | BS30: 2908.8 | BW30: 杭州中冠电器有限公司 | BX30: 2908.8 | BZ30: 人民币 | CA30: 否 | CB30: 2025/10/9 | CC30: 是 | CD30: YSJ.00042 | CE30: R1700FWi饮水机 | CF30: A20251002000983 | CG30: 1 | CH30: 否 | CK30: 10.2刷卡3636元（2908.8+补贴727.20元）【用户姓名:张艳佳；用户手机:18357002327；其他号码: 】 | CL30: 2908.8 | CN30: 人民币 | CO30: 固定汇率 | CT30: 杭州地区客户 | CW30: 否 | DD30: 未关闭 | DK30: 张艳佳 | DL30: 18357002327
A31: 现款现货收款单 | B31: SKD251003150 | C31: 杭州 | D31: 2025/10/9 | E31: 客户 | F31: 客户 | G31: 人民币 | H31: 727.2 | I31: 727.2 | J31: 杭州中冠电器有限公司 | L31: 杭州中冠电器有限公司 | M31: 杭州红星美凯龙一号店 | N31: 杭州大区 | P31: 727.2 | Q31: 吴红玉 | R31: 人民币 | S31: 固定汇率 | T31: 1 | U31: 727.2 | V31: 727.2 | X31: 完全 | Z31: 销售业务 | AA31: 信用正常 | AB31: 转账 | AC31: 预收款 | AD31: 销售订单 | AE31: 1 | AF31: A20251002000983 | AG31: 727.2 | AI31: 727.2 | AJ31: 727.2 | AM31: 727.2 | AN31: 政府以旧换新中转银行 | AO31: 否 | AP31: 政府以旧换新中转银行 | AQ31: 手工新增 | AS31: 杭州红星美凯龙一号店 | AX31: 727.2 | AY31: 否 | AZ31: 9999999 | BA31: 727.2 | BC31: 否 | BD31: 727.2 | BE31: 完全 | BF31: 727.2 | BH31: 727.2 | BI31: 已审核 | BJ31: 陈联 | BK31: 陈联 | BL31: 桑玲 | BM31: 2025/10/3 | BN31: 2025-10-03 14:55:28 | BO31: 2025-10-06 14:24:13 | BR31: 否 | BS31: 727.2 | BW31: 杭州中冠电器有限公司 | BX31: 727.2 | BZ31: 人民币 | CA31: 否 | CB31: 2025/10/9 | CC31: 是 | CD31: YSJ.00042 | CE31: R1700FWi饮水机 | CF31: A20251002000983 | CG31: 1 | CH31: 否 | CK31: 10.2刷卡3636元（2908.8+补贴727.20元）【用户姓名:张艳佳；用户手机:18357002327；其他号码: 】 | CL31: 727.2 | CN31: 人民币 | CO31: 固定汇率 | CT31: 杭州地区客户 | CW31: 否 | DD31: 未关闭 | DK31: 张艳佳 | DL31: 18357002327
A32: 现款现货收款单 | B32: SKD251003152 | C32: 湖州 | D32: 2025/10/3 | E32: 客户 | F32: 客户 | G32: 人民币 | H32: 4481 | I32: 4481 | J32: 杭州中冠电器有限公司 | L32: 杭州中冠电器有限公司 | M32: 湖州金蝶零售 | N32: 湖州办事处 | P32: 4481 | Q32: 陈中元 | R32: 人民币 | S32: 固定汇率 | T32: 1 | U32: 4481 | V32: 4481 | X32: 完全 | Z32: 销售业务 | AA32: 信用正常 | AB32: 转账 | AC32: 预收款 | AD32: 销售订单 | AE32: 1 | AF32: XSDD251003011 | AG32: 4481 | AI32: 4481 | AJ32: 4481 | AM32: 4481 | AN32: 杭州中冠电器有限公司 | AO32: 否 | AP32: 中信银行杭州钱江支行 | AQ32: 手工新增 | AS32: 湖州金蝶零售 | AX32: 4481 | AY32: 否 | AZ32: 7331710182200026317 | BA32: 4481 | BC32: 否 | BD32: 4481 | BE32: 完全 | BF32: 4481 | BH32: 4481 | BI32: 已审核 | BJ32: 陈联 | BK32: 陈联 | BL32: 桑玲 | BM32: 2025/10/3 | BN32: 2025-10-03 15:35:22 | BO32: 2025-10-03 15:38:27 | BR32: 否 | BS32: 4481 | BW32: 杭州中冠电器有限公司 | BX32: 4481 | BZ32: 人民币 | CA32: 否 | CB32: 2025/10/3 | CC32: 是 | CD32: RQRS.00009 | CE32: JSQ31-CSCAi燃气快速热水器通用 | CF32: XSDD251003011 | CG32: 1 | CH32: 否 | CK32: 10.3转账4481元【用户姓名:湖州中太芯猫科技有限公司；用户手机:1315725269；其他号码: 】 | CL32: 4481 | CN32: 人民币 | CO32: 固定汇率 | CT32: 湖州-主城 | CW32: 否 | DD32: 未关闭 | DK32: 湖州中太芯猫科技有限公司 | DL32: 1315725269
A33: 现款现货收款单 | B33: SKD251003153 | C33: 杭州 | D33: 2025/10/3 | E33: 客户 | F33: 客户 | G33: 人民币 | H33: 6365 | I33: 6365 | J33: 杭州中冠电器有限公司 | L33: 杭州中冠电器有限公司 | M33: 萧山第六空间专卖店 | N33: 杭州大区 | P33: 6365 | Q33: 徐美娟 | R33: 人民币 | S33: 固定汇率 | T33: 1 | U33: 6365 | V33: 6365 | X33: 完全 | Z33: 销售业务 | AA33: 信用正常 | AB33: 转账 | AC33: 预收款 | AD33: 销售订单 | AE33: 1 | AF33: A20251003000556 | AG33: 6365 | AI33: 6365 | AJ33: 6365 | AM33: 6365 | AN33: 杭州中冠电器有限公司支付宝 | AO33: 否 | AP33: 杭州中冠电器有限公司支付宝 | AQ33: 手工新增 | AS33: 萧山第六空间专卖店 | AX33: 6365 | AY33: 否 | AZ33: hzzgcw@163.com | BA33: 6365 | BC33: 否 | BD33: 6365 | BE33: 完全 | BF33: 6365 | BH33: 6365 | BI33: 已审核 | BJ33: 陈联 | BK33: 陈联 | BL33: 桑玲 | BM33: 2025/10/3 | BN33: 2025-10-03 15:51:44 | BO33: 2025-10-03 15:52:39 | BR33: 否 | BS33: 6365 | BW33: 杭州中冠电器有限公司 | BX33: 6365 | BZ33: 人民币 | CA33: 否 | CB33: 2025/10/3 | CC33: 是 | CD33: YSJ.00013 | CE33: DR1800HF2Ai反渗透净水机 | CF33: A20251003000556 | CG33: 1 | CH33: 否 | CK33: 10.3支付宝6365元【用户姓名:陈海军；用户手机:13616539181；其他号码: 】 | CL33: 6365 | CN33: 人民币 | CO33: 固定汇率 | CT33: 杭州-萧山 | CW33: 否 | DD33: 未关闭 | DK33: 陈海军 | DL33: 13616539181 | DR33: 2025100322001438391430215115
A34: 现款现货收款单 | B34: SKD251004017 | C34: 杭州 | D34: 2025/10/9 | E34: 客户 | F34: 客户 | G34: 人民币 | H34: 3717.6 | I34: 3695.29 | J34: 杭州中冠电器有限公司 | L34: 杭州中冠电器有限公司 | M34: 滨江六空8090店 | N34: 杭州大区 | P34: 3717.6 | Q34: 葛芬 | R34: 人民币 | S34: 固定汇率 | T34: 1 | U34: 3717.6 | V34: 3695.29 | X34: 完全 | Z34: 销售业务 | AA34: 信用正常 | AB34: 转账 | AC34: 预收款 | AD34: 销售订单 | AE34: 1 | AF34: A20251004001163 | AG34: 3717.6 | AI34: 3717.6 | AJ34: 3717.6 | AK34: 22.31 | AM34: 3695.29 | AN34: 杭州中冠电器有限公司 | AO34: 否 | AP34: 中信银行杭州钱江支行 | AQ34: 手工新增 | AS34: 滨江六空8090店 | AX34: 3717.6 | AY34: 否 | AZ34: 7331710182200026317 | BA34: 3717.6 | BC34: 否 | BD34: 3717.6 | BE34: 完全 | BF34: 3717.6 | BG34: 22.31 | BH34: 3695.29 | BI34: 已审核 | BJ34: 葛 芬 | BK34: 桑玲 | BL34: 桑玲 | BM34: 2025/10/4 | BN34: 2025-10-07 09:36:15 | BO34: 2025-10-06 12:53:16 | BR34: 否 | BS34: 3717.6 | BW34: 杭州中冠电器有限公司 | BX34: 3717.6 | BZ34: 人民币 | CA34: 否 | CB34: 2025/10/9 | CC34: 是 | CD34: YSJ.00040 | CE34: R2000FWi饮水机 | CF34: A20251004001163 | CG34: 1 | CH34: 否 | CK34: 10.3刷卡4647元(3717.6元+补贴929.4元）（用户名 刘利）【用户姓名:刘利；用户手机:15268117016；其他号码: 】 | CL34: 3717.6 | CN34: 人民币 | CO34: 固定汇率 | CT34: 杭州-主城 | CW34: 否 | DD34: 未关闭 | DK34: 刘利 | DL34: 15268117016
A35: 现款现货收款单 | B35: SKD251004018 | C35: 杭州 | D35: 2025/10/9 | E35: 客户 | F35: 客户 | G35: 人民币 | H35: 929.4 | I35: 929.4 | J35: 杭州中冠电器有限公司 | L35: 杭州中冠电器有限公司 | M35: 滨江六空8090店 | N35: 杭州大区 | P35: 929.4 | Q35: 葛芬 | R35: 人民币 | S35: 固定汇率 | T35: 1 | U35: 929.4 | V35: 929.4 | X35: 完全 | Z35: 销售业务 | AA35: 信用正常 | AB35: 转账 | AC35: 预收款 | AD35: 销售订单 | AE35: 1 | AF35: A20251004001163 | AG35: 929.4 | AI35: 929.4 | AJ35: 929.4 | AM35: 929.4 | AN35: 政府以旧换新中转银行 | AO35: 否 | AP35: 政府以旧换新中转银行 | AQ35: 手工新增 | AS35: 滨江六空8090店 | AX35: 929.4 | AY35: 否 | AZ35: 9999999 | BA35: 929.4 | BC35: 否 | BD35: 929.4 | BE35: 完全 | BF35: 929.4 | BH35: 929.4 | BI35: 已审核 | BJ35: 葛 芬 | BK35: 葛 芬 | BL35: 桑玲 | BM35: 2025/10/4 | BN35: 2025-10-04 11:52:01 | BO35: 2025-10-06 12:53:31 | BR35: 否 | BS35: 929.4 | BW35: 杭州中冠电器有限公司 | BX35: 929.4 | BZ35: 人民币 | CA35: 否 | CB35: 2025/10/9 | CC35: 是 | CD35: YSJ.00040 | CE35: R2000FWi饮水机 | CF35: A20251004001163 | CG35: 1 | CH35: 否 | CK35: 10.3刷卡4647元(3717.6元+补贴929.4元）（用户名 刘利）【用户姓名:刘利；用户手机:15268117016；其他号码: 】 | CL35: 929.4 | CN35: 人民币 | CO35: 固定汇率 | CT35: 杭州-主城 | CW35: 否 | DD35: 未关闭 | DK35: 刘利 | DL35: 15268117016
A36: 现款现货收款单 | B36: SKD251004050 | C36: 杭州 | D36: 2025/10/4 | E36: 客户 | F36: 客户 | G36: 人民币 | H36: 5000 | I36: 5000 | J36: 杭州中冠电器有限公司 | L36: 杭州中冠电器有限公司 | M36: 杭州临平江南家居专卖店 | N36: 杭州大区 | P36: 5000 | Q36: 余亚炜 | R36: 人民币 | S36: 固定汇率 | T36: 1 | U36: 5000 | V36: 5000 | X36: 完全 | Z36: 销售业务 | AA36: 信用正常 | AB36: 转账 | AC36: 预收款 | AD36: 销售订单 | AE36: 1 | AF36: A20251004000621 | AG36: 5000 | AI36: 5000 | AJ36: 5000 | AM36: 5000 | AN36: 杭州中冠电器有限公司支付宝 | AO36: 否 | AP36: 杭州中冠电器有限公司支付宝 | AQ36: 手工新增 | AS36: 杭州临平江南家居专卖店 | AX36: 5000 | AY36: 否 | AZ36: hzzgcw@163.com | BA36: 5000 | BC36: 否 | BD36: 5000 | BE36: 完全 | BF36: 5000 | BH36: 5000 | BI36: 已审核 | BJ36: 余亚炜 | BK36: 余亚炜 | BL36: 桑玲 | BM36: 2025/10/4 | BN36: 2025-10-04 14:54:45 | BO36: 2025-10-06 12:54:03 | BR36: 否 | BS36: 5000 | BW36: 杭州中冠电器有限公司 | BX36: 5000 | BZ36: 人民币 | CA36: 否 | CB36: 2025/10/4 | CC36: 是 | CD36: YYJ.00008 | CE36: CXW-200-Q3AWi易清洁顶侧双吸油烟机 | CF36: A20251004000621 | CG36: 1 | CH36: 否 | CK36: 10.4扫码转支付宝5000元【用户姓名:徐广东；用户手机:13683762291；其他号码: 】 | CL36: 5000 | CN36: 人民币 | CO36: 固定汇率 | CT36: 杭州-余杭 | CW36: 否 | DD36: 未关闭 | DK36: 徐广东 | DL36: 13683762291 | DR36: 2025100422001497631442263144
A37: 销售收款单 | B37: SKD251004086 | C37: 杭州 | D37: 2025/10/2 | E37: 客户 | F37: 客户 | G37: 人民币 | H37: 17300 | I37: 17187.53 | J37: 杭州中冠电器有限公司 | L37: 杭州中冠电器有限公司 | M37: 自营以旧换新特别账户 | N37: 销管部 | P37: 17300 | Q37: 罗清 | R37: 人民币 | S37: 固定汇率 | T37: 1 | U37: 17300 | V37: 17187.53 | X37: 空 | Z37: 销售业务 | AA37: 信用正常 | AB37: 转账 | AC37: 销售收款 | AE37: 1 | AG37: 3290 | AI37: 17300 | AJ37: 3290 | AK37: 21.39 | AM37: 3268.61 | AN37: 杭州中冠电器有限公司 | AO37: 否 | AP37: 中信银行杭州钱江支行 | AQ37: 手工新增 | AS37: 自营以旧换新特别账户 | AX37: 3290 | AY37: 否 | AZ37: 7331710182200026317 | BA37: 3290 | BB37: 2025年10月用户结算(换新5） | BC37: 否 | BE37: 空 | BG37: 21.39 | BH37: 3268.61 | BI37: 已审核 | BJ37: 毛银萍 | BK37: 桑玲 | BL37: 桑玲 | BM37: 2025/10/4 | BN37: 2025-10-07 09:47:48 | BO37: 2025-10-07 09:47:49 | BR37: 否 | BS37: 3290 | BW37: 杭州中冠电器有限公司 | BZ37: 人民币 | CA37: 否 | CB37: 2025/10/2 | CC37: 是 | CH37: 否 | CK37: 2025年10月2日中信银行收款【用户姓名:2025年10月结算(换新5-10）；用户手机: ；其他号码: 】 | CN37: 人民币 | CO37: 固定汇率 | CT37: 杭州-主城 | CW37: 否 | DD37: 未关闭 | DK37: 2025年10月结算(换新5-10） | DR37: 2025年10月结算(换新5-10）
AB38: 转账 | AC38: 销售收款 | AG38: 2976 | AJ38: 2976 | AK38: 19.35 | AM38: 2956.65 | AN38: 杭州中冠电器有限公司 | AP38: 中信银行杭州钱江支行 | AX38: 2976 | AZ38: 7331710182200026317 | BA38: 2976 | BB38: 2025年10月客户结算(换新6） | BC38: 否 | BE38: 空 | BG38: 19.35 | BH38: 2956.65 | BS38: 2976 | CB38: 2025/10/2 | CC38: 是 | DD38: 未关闭
AB39: 转账 | AC39: 销售收款 | AG39: 2976 | AJ39: 2976 | AK39: 19.35 | AM39: 2956.65 | AN39: 杭州中冠电器有限公司 | AP39: 中信银行杭州钱江支行 | AX39: 2976 | AZ39: 7331710182200026317 | BA39: 2976 | BB39: 2025年10月唐宇魁结算(换新7） | BC39: 否 | BE39: 空 | BG39: 19.35 | BH39: 2956.65 | BS39: 2976 | CB39: 2025/10/2 | CC39: 是 | DD39: 未关闭
AB40: 转账 | AC40: 销售收款 | AG40: 2686 | AJ40: 2686 | AK40: 17.46 | AM40: 2668.54 | AN40: 杭州中冠电器有限公司 | AP40: 中信银行杭州钱江支行 | AX40: 2686 | AZ40: 7331710182200026317 | BA40: 2686 | BB40: 2025年10月侯新波结算(换新8） | BC40: 否 | BE40: 空 | BG40: 17.46 | BH40: 2668.54 | BS40: 2686 | CB40: 2025/10/2 | CC40: 是 | DD40: 未关闭
AB41: 转账 | AC41: 销售收款 | AG41: 2686 | AJ41: 2686 | AK41: 17.46 | AM41: 2668.54 | AN41: 杭州中冠电器有限公司 | AP41: 中信银行杭州钱江支行 | AX41: 2686 | AZ41: 7331710182200026317 | BA41: 2686 | BB41: 2025年10月徐露莎结算(换新9） | BC41: 否 | BE41: 空 | BG41: 17.46 | BH41: 2668.54 | BS41: 2686 | CB41: 2025/10/2 | CC41: 是 | DD41: 未关闭
AB42: 转账 | AC42: 销售收款 | AG42: 2686 | AJ42: 2686 | AK42: 17.46 | AM42: 2668.54 | AN42: 杭州中冠电器有限公司 | AP42: 中信银行杭州钱江支行 | AX42: 2686 | AZ42: 7331710182200026317 | BA42: 2686 | BB42: 2025年10月徐晓单结算(换新10） | BC42: 否 | BE42: 空 | BG42: 17.46 | BH42: 2668.54 | BS42: 2686 | CB42: 2025/10/2 | CC42: 是 | DD42: 未关闭
A43: 销售收款单 | B43: SKD251004087 | C43: 杭州 | D43: 2025/10/3 | E43: 客户 | F43: 客户 | G43: 人民币 | H43: 17592 | I43: 17477.65 | J43: 杭州中冠电器有限公司 | L43: 杭州中冠电器有限公司 | M43: 自营以旧换新特别账户 | N43: 销管部 | P43: 17592 | Q43: 罗清 | R43: 人民币 | S43: 固定汇率 | T43: 1 | U43: 17592 | V43: 17477.65 | X43: 空 | Z43: 销售业务 | AA43: 信用正常 | AB43: 转账 | AC43: 销售收款 | AE43: 1 | AG43: 3460 | AI43: 17592 | AJ43: 3460 | AK43: 22.49 | AM43: 3437.51 | AN43: 杭州中冠电器有限公司 | AO43: 否 | AP43: 中信银行杭州钱江支行 | AQ43: 手工新增 | AS43: 自营以旧换新特别账户 | AX43: 3460 | AY43: 否 | AZ43: 7331710182200026317 | BA43: 3460 | BB43: 2025年10月潘结算(换新11） | BC43: 否 | BE43: 空 | BG43: 22.49 | BH43: 3437.51 | BI43: 已审核 | BJ43: 毛银萍 | BK43: 桑玲 | BL43: 桑玲 | BM43: 2025/10/4 | BN43: 2025-10-07 09:49:21 | BO43: 2025-10-07 09:49:22 | BR43: 否 | BS43: 3460 | BW43: 杭州中冠电器有限公司 | BZ43: 人民币 | CA43: 否 | CB43: 2025/10/3 | CC43: 是 | CH43: 否 | CK43: 2025年10月3日中信银行收款【用户姓名:2025年10月结算(换新11-16）；用户手机: ；其他号码: 】 | CN43: 人民币 | CO43: 固定汇率 | CT43: 杭州-主城 | CW43: 否 | DD43: 未关闭 | DK43: 2025年10月结算(换新11-16） | DR43: 2025年10月结算(换新11-16）
AB44: 转账 | AC44: 销售收款 | AG44: 2686 | AJ44: 2686 | AK44: 17.46 | AM44: 2668.54 | AN44: 杭州中冠电器有限公司 | AP44: 中信银行杭州钱江支行 | AX44: 2686 | AZ44: 7331710182200026317 | BA44: 2686 | BB44: 2025年10月徐耀萍结算(换新12） | BC44: 否 | BE44: 空 | BG44: 17.46 | BH44: 2668.54 | BS44: 2686 | CB44: 2025/10/3 | CC44: 是 | DD44: 未关闭
AB45: 转账 | AC45: 销售收款 | AG45: 2686 | AJ45: 2686 | AK45: 17.46 | AM45: 2668.54 | AN45: 杭州中冠电器有限公司 | AP45: 中信银行杭州钱江支行 | AX45: 2686 | AZ45: 7331710182200026317 | BA45: 2686 | BB45: 2025年10月吴凤燕结算(换新13） | BC45: 否 | BE45: 空 | BG45: 17.46 | BH45: 2668.54 | BS45: 2686 | CB45: 2025/10/3 | CC45: 是 | DD45: 未关闭
AB46: 转账 | AC46: 销售收款 | AG46: 2686 | AJ46: 2686 | AK46: 17.46 | AM46: 2668.54 | AN46: 杭州中冠电器有限公司 | AP46: 中信银行杭州钱江支行 | AX46: 2686 | AZ46: 7331710182200026317 | BA46: 2686 | BB46: 2025年10月王总结算(换新14） | BC46: 否 | BE46: 空 | BG46: 17.46 | BH46: 2668.54 | BS46: 2686 | CB46: 2025/10/3 | CC46: 是 | DD46: 未关闭
AB47: 转账 | AC47: 销售收款 | AG47: 3460 | AJ47: 3460 | AK47: 22.49 | AM47: 3437.51 | AN47: 杭州中冠电器有限公司 | AP47: 中信银行杭州钱江支行 | AX47: 3460 | AZ47: 7331710182200026317 | BA47: 3460 | BB47: 2025年10月客户结算(换新15） | BC47: 否 | BE47: 空 | BG47: 22.49 | BH47: 3437.51 | BS47: 3460 | CB47: 2025/10/3 | CC47: 是 | DD47: 未关闭
AB48: 转账 | AC48: 销售收款 | AG48: 2614 | AJ48: 2614 | AK48: 16.99 | AM48: 2597.01 | AN48: 杭州中冠电器有限公司 | AP48: 中信银行杭州钱江支行 | AX48: 2614 | AZ48: 7331710182200026317 | BA48: 2614 | BB48: 2025年10月陆先生结算(换新16） | BC48: 否 | BE48: 空 | BG48: 16.99 | BH48: 2597.01 | BS48: 2614 | CB48: 2025/10/3 | CC48: 是 | DD48: 未关闭
A49: 销售收款单 | B49: SKD251004088 | C49: 杭州 | D49: 2025/10/4 | E49: 客户 | F49: 客户 | G49: 人民币 | H49: 25305 | I49: 25140.51 | J49: 杭州中冠电器有限公司 | L49: 杭州中冠电器有限公司 | M49: 自营以旧换新特别账户 | N49: 销管部 | P49: 25305 | Q49: 罗清 | R49: 人民币 | S49: 固定汇率 | T49: 1 | U49: 25305 | V49: 25140.51 | X49: 空 | Z49: 销售业务 | AA49: 信用正常 | AB49: 转账 | AC49: 销售收款 | AE49: 1 | AG49: 2686 | AI49: 25305 | AJ49: 2686 | AK49: 17.46 | AM49: 2668.54 | AN49: 杭州中冠电器有限公司 | AO49: 否 | AP49: 中信银行杭州钱江支行 | AQ49: 手工新增 | AS49: 自营以旧换新特别账户 | AX49: 2686 | AY49: 否 | AZ49: 7331710182200026317 | BA49: 2686 | BB49: 2025年10月古祥结算(换新17） | BC49: 否 | BE49: 空 | BG49: 17.46 | BH49: 2668.54 | BI49: 已审核 | BJ49: 毛银萍 | BK49: 桑玲 | BL49: 桑玲 | BM49: 2025/10/4 | BN49: 2025-10-07 09:51:38 | BO49: 2025-10-07 09:51:39 | BR49: 否 | BS49: 2686 | BW49: 杭州中冠电器有限公司 | BZ49: 人民币 | CA49: 否 | CB49: 2025/10/4 | CC49: 是 | CH49: 否 | CK49: 2025年10月4日中信银行收款【用户姓名:2025年10月结算(换新17-24）；用户手机: ；其他号码: 】 | CN49: 人民币 | CO49: 固定汇率 | CT49: 杭州-主城 | CW49: 否 | DD49: 未关闭 | DK49: 2025年10月结算(换新17-24） | DR49: 2025年10月结算(换新17-24）
AB50: 转账 | AC50: 销售收款 | AG50: 2686 | AJ50: 2686 | AK50: 17.46 | AM50: 2668.54 | AN50: 杭州中冠电器有限公司 | AP50: 中信银行杭州钱江支行 | AX50: 2686 | AZ50: 7331710182200026317 | BA50: 2686 | BB50: 2025年10月楼静洁结算(换新18） | BC50: 否 | BE50: 空 | BG50: 17.46 | BH50: 2668.54 | BS50: 2686 | CB50: 2025/10/4 | CC50: 是 | DD50: 未关闭
AB51: 转账 | AC51: 销售收款 | AG51: 6002 | AJ51: 6002 | AK51: 39.01 | AM51: 5962.99 | AN51: 杭州中冠电器有限公司 | AP51: 中信银行杭州钱江支行 | AX51: 6002 | AZ51: 7331710182200026317 | BA51: 6002 | BB51: 2025年10月杨惠民结算(换新19） | BC51: 否 | BE51: 空 | BG51: 39.01 | BH51: 5962.99 | BS51: 6002 | CB51: 2025/10/4 | CC51: 是 | DD51: 未关闭
AB52: 转账 | AC52: 销售收款 | AG52: 2686 | AJ52: 2686 | AK52: 17.46 | AM52: 2668.54 | AN52: 杭州中冠电器有限公司 | AP52: 中信银行杭州钱江支行 | AX52: 2686 | AZ52: 7331710182200026317 | BA52: 2686 | BB52: 2025年10月刘小芬结算(换新20） | BC52: 否 | BE52: 空 | BG52: 17.46 | BH52: 2668.54 | BS52: 2686 | CB52: 2025/10/4 | CC52: 是 | DD52: 未关闭
AB53: 转账 | AC53: 销售收款 | AG53: 2686 | AJ53: 2686 | AK53: 17.46 | AM53: 2668.54 | AN53: 杭州中冠电器有限公司 | AP53: 中信银行杭州钱江支行 | AX53: 2686 | AZ53: 7331710182200026317 | BA53: 2686 | BB53: 2025年10月潘先生结算(换新21） | BC53: 否 | BE53: 空 | BG53: 17.46 | BH53: 2668.54 | BS53: 2686 | CB53: 2025/10/4 | CC53: 是 | DD53: 未关闭
AB54: 转账 | AC54: 销售收款 | AG54: 2686 | AJ54: 2686 | AK54: 17.46 | AM54: 2668.54 | AN54: 杭州中冠电器有限公司 | AP54: 中信银行杭州钱江支行 | AX54: 2686 | AZ54: 7331710182200026317 | BA54: 2686 | BB54: 2025年10月袁秋燕结算(换新22） | BC54: 否 | BE54: 空 | BG54: 17.46 | BH54: 2668.54 | BS54: 2686 | CB54: 2025/10/4 | CC54: 是 | DD54: 未关闭
AB55: 转账 | AC55: 销售收款 | AG55: 3701 | AJ55: 3701 | AK55: 24.06 | AM55: 3676.94 | AN55: 杭州中冠电器有限公司 | AP55: 中信银行杭州钱江支行 | AX55: 3701 | AZ55: 7331710182200026317 | BA55: 3701 | BB55: 2025年10月徐效结算(换新23） | BC55: 否 | BE55: 空 | BG55: 24.06 | BH55: 3676.94 | BS55: 3701 | CB55: 2025/10/4 | CC55: 是 | DD55: 未关闭
AB56: 转账 | AC56: 销售收款 | AG56: 2172 | AJ56: 2172 | AK56: 14.12 | AM56: 2157.88 | AN56: 杭州中冠电器有限公司 | AP56: 中信银行杭州钱江支行 | AX56: 2172 | AZ56: 7331710182200026317 | BA56: 2172 | BB56: 2025年10月徐倩结算(换新24） | BC56: 否 | BE56: 空 | BG56: 14.12 | BH56: 2157.88 | BS56: 2172 | CB56: 2025/10/4 | CC56: 是 | DD56: 未关闭
A57: 销售收款单 | B57: SKD251004089 | C57: 杭州 | D57: 2025/10/5 | E57: 客户 | F57: 客户 | G57: 人民币 | H57: 22658 | I57: 22510.72 | J57: 杭州中冠电器有限公司 | L57: 杭州中冠电器有限公司 | M57: 自营以旧换新特别账户 | N57: 销管部 | P57: 22658 | Q57: 罗清 | R57: 人民币 | S57: 固定汇率 | T57: 1 | U57: 22658 | V57: 22510.72 | X57: 空 | Z57: 销售业务 | AA57: 信用正常 | AB57: 转账 | AC57: 销售收款 | AE57: 1 | AG57: 2686 | AI57: 22658 | AJ57: 2686 | AK57: 17.46 | AM57: 2668.54 | AN57: 杭州中冠电器有限公司 | AO57: 否 | AP57: 中信银行杭州钱江支行 | AQ57: 手工新增 | AS57: 自营以旧换新特别账户 | AX57: 2686 | AY57: 否 | AZ57: 7331710182200026317 | BA57: 2686 | BB57: 2025年10月虎风结算(换新25） | BC57: 否 | BE57: 空 | BG57: 17.46 | BH57: 2668.54 | BI57: 已审核 | BJ57: 毛银萍 | BK57: 桑玲 | BL57: 桑玲 | BM57: 2025/10/4 | BN57: 2025-10-07 09:54:16 | BO57: 2025-10-07 09:54:17 | BR57: 否 | BS57: 2686 | BW57: 杭州中冠电器有限公司 | BZ57: 人民币 | CA57: 否 | CB57: 2025/10/5 | CC57: 是 | CH57: 否 | CK57: 2025年10月5日中信银行收款【用户姓名:2025年10月结算(换新25-31）；用户手机: ；其他号码: 】 | CN57: 人民币 | CO57: 固定汇率 | CT57: 杭州-主城 | CW57: 否 | DD57: 未关闭 | DK57: 2025年10月结算(换新25-31） | DR57: 2025年10月结算(换新25-31）
AB58: 转账 | AC58: 销售收款 | AG58: 2686 | AJ58: 2686 | AK58: 17.46 | AM58: 2668.54 | AN58: 杭州中冠电器有限公司 | AP58: 中信银行杭州钱江支行 | AX58: 2686 | AZ58: 7331710182200026317 | BA58: 2686 | BB58: 2025年10月吴小萍结算(换新26） | BC58: 否 | BE58: 空 | BG58: 17.46 | BH58: 2668.54 | BS58: 2686 | CB58: 2025/10/5 | CC58: 是 | DD58: 未关闭
AB59: 转账 | AC59: 销售收款 | AG59: 3932 | AJ59: 3932 | AK59: 25.56 | AM59: 3906.44 | AN59: 杭州中冠电器有限公司 | AP59: 中信银行杭州钱江支行 | AX59: 3932 | AZ59: 7331710182200026317 | BA59: 3932 | BB59: 2025年10月陈星结算(换新27） | BC59: 否 | BE59: 空 | BG59: 25.56 | BH59: 3906.44 | BS59: 3932 | CB59: 2025/10/5 | CC59: 是 | DD59: 未关闭
AB60: 转账 | AC60: 销售收款 | AG60: 4344 | AJ60: 4344 | AK60: 28.23 | AM60: 4315.77 | AN60: 杭州中冠电器有限公司 | AP60: 中信银行杭州钱江支行 | AX60: 4344 | AZ60: 7331710182200026317 | BA60: 4344 | BB60: 2025年10月冯新结算(换新28） | BC60: 否 | BE60: 空 | BG60: 28.23 | BH60: 4315.77 | BS60: 4344 | CB60: 2025/10/5 | CC60: 是 | DD60: 未关闭
AB61: 转账 | AC61: 销售收款 | AG61: 3460 | AJ61: 3460 | AK61: 22.49 | AM61: 3437.51 | AN61: 杭州中冠电器有限公司 | AP61: 中信银行杭州钱江支行 | AX61: 3460 | AZ61: 7331710182200026317 | BA61: 3460 | BB61: 2025年10月陆丽伟结算(换新29） | BC61: 否 | BE61: 空 | BG61: 22.49 | BH61: 3437.51 | BS61: 3460 | CB61: 2025/10/5 | CC61: 是 | DD61: 未关闭
AB62: 转账 | AC62: 销售收款 | AG62: 2574 | AJ62: 2574 | AK62: 16.73 | AM62: 2557.27 | AN62: 杭州中冠电器有限公司 | AP62: 中信银行杭州钱江支行 | AX62: 2574 | AZ62: 7331710182200026317 | BA62: 2574 | BB62: 2025年10月吴军结算(换新30） | BC62: 否 | BE62: 空 | BG62: 16.73 | BH62: 2557.27 | BS62: 2574 | CB62: 2025/10/5 | CC62: 是 | DD62: 未关闭
AB63: 转账 | AC63: 销售收款 | AG63: 2976 | AJ63: 2976 | AK63: 19.35 | AM63: 2956.65 | AN63: 杭州中冠电器有限公司 | AP63: 中信银行杭州钱江支行 | AX63: 2976 | AZ63: 7331710182200026317 | BA63: 2976 | BB63: 2025年10月用户结算(换新31） | BC63: 否 | BE63: 空 | BG63: 19.35 | BH63: 2956.65 | BS63: 2976 | CB63: 2025/10/5 | CC63: 是 | DD63: 未关闭
A64: 销售收款单 | B64: SKD251004090 | C64: 杭州 | D64: 2025/10/6 | E64: 客户 | F64: 客户 | G64: 人民币 | H64: 10731 | I64: 10661.25 | J64: 杭州中冠电器有限公司 | L64: 杭州中冠电器有限公司 | M64: 自营以旧换新特别账户 | N64: 销管部 | P64: 10731 | Q64: 罗清 | R64: 人民币 | S64: 固定汇率 | T64: 1 | U64: 10731 | V64: 10661.25 | X64: 空 | Z64: 销售业务 | AA64: 信用正常 | AB64: 转账 | AC64: 销售收款 | AE64: 1 | AG64: 4344 | AI64: 10731 | AJ64: 4344 | AK64: 28.23 | AM64: 4315.77 | AN64: 杭州中冠电器有限公司 | AO64: 否 | AP64: 中信银行杭州钱江支行 | AQ64: 手工新增 | AS64: 自营以旧换新特别账户 | AX64: 4344 | AY64: 否 | AZ64: 7331710182200026317 | BA64: 4344 | BB64: 2025年10月客户结算(换新32） | BC64: 否 | BE64: 空 | BG64: 28.23 | BH64: 4315.77 | BI64: 已审核 | BJ64: 毛银萍 | BK64: 桑玲 | BL64: 桑玲 | BM64: 2025/10/4 | BN64: 2025-10-07 15:20:36 | BO64: 2025-10-07 15:20:38 | BR64: 否 | BS64: 4344 | BW64: 杭州中冠电器有限公司 | BZ64: 人民币 | CA64: 否 | CB64: 2025/10/6 | CC64: 是 | CH64: 否 | CK64: 2025年10月6日中信银行收款【用户姓名:2025年10月结算(换新32-34）；用户手机: ；其他号码: 】 | CN64: 人民币 | CO64: 固定汇率 | CT64: 杭州-主城 | CW64: 否 | DD64: 未关闭 | DK64: 2025年10月结算(换新32-34） | DR64: 2025年10月结算(换新32-34）
AB65: 转账 | AC65: 销售收款 | AG65: 2686 | AJ65: 2686 | AK65: 17.46 | AM65: 2668.54 | AN65: 杭州中冠电器有限公司 | AP65: 中信银行杭州钱江支行 | AX65: 2686 | AZ65: 7331710182200026317 | BA65: 2686 | BB65: 2025年10月白希来结算(换新33） | BC65: 否 | BE65: 空 | BG65: 17.46 | BH65: 2668.54 | BS65: 2686 | CB65: 2025/10/6 | CC65: 是 | DD65: 未关闭
AB66: 转账 | AC66: 销售收款 | AG66: 3701 | AJ66: 3701 | AK66: 24.06 | AM66: 3676.94 | AN66: 杭州中冠电器有限公司 | AP66: 中信银行杭州钱江支行 | AX66: 3701 | AZ66: 7331710182200026317 | BA66: 3701 | BB66: 2025年10月戴女士结算(换新34） | BC66: 否 | BE66: 空 | BG66: 24.06 | BH66: 3676.94 | BS66: 3701 | CB66: 2025/10/6 | CC66: 是 | DD66: 未关闭
A67: 现款现货收款单 | B67: SKD251005062 | C67: 杭州 | D67: 2025/10/9 | E67: 客户 | F67: 客户 | G67: 人民币 | H67: 4015.2 | I67: 3991.11 | J67: 杭州中冠电器有限公司 | L67: 杭州中冠电器有限公司 | M67: 滨江六空8090店 | N67: 杭州大区 | P67: 4015.2 | Q67: 葛芬 | R67: 人民币 | S67: 固定汇率 | T67: 1 | U67: 4015.2 | V67: 3991.11 | X67: 完全 | Z67: 销售业务 | AA67: 信用正常 | AB67: 转账 | AC67: 预收款 | AD67: 销售订单 | AE67: 1 | AF67: A20251005000961 | AG67: 4015.2 | AI67: 4015.2 | AJ67: 4015.2 | AK67: 24.09 | AM67: 3991.11 | AN67: 杭州中冠电器有限公司 | AO67: 否 | AP67: 中信银行杭州钱江支行 | AQ67: 手工新增 | AS67: 滨江六空8090店 | AX67: 4015.2 | AY67: 否 | AZ67: 7331710182200026317 | BA67: 4015.2 | BC67: 否 | BD67: 4015.2 | BE67: 完全 | BF67: 4015.2 | BG67: 24.09 | BH67: 3991.11 | BI67: 已审核 | BJ67: 葛 芬 | BK67: 桑玲 | BL67: 桑玲 | BM67: 2025/10/5 | BN67: 2025-10-07 09:38:46 | BO67: 2025-10-06 12:54:42 | BR67: 否 | BS67: 4015.2 | BW67: 杭州中冠电器有限公司 | BX67: 4015.2 | BZ67: 人民币 | CA67: 否 | CB67: 2025/10/9 | CC67: 是 | CD67: DRSQ.00027 | CE67: EWH-80HGCWi薄型电热水器 | CF67: A20251005000961 | CG67: 1 | CH67: 否 | CK67: 10.4刷卡5019元(4015.2元+补贴1003.8元）（用户名 冯泽英）【用户姓名:冯泽英；用户手机:13094805606；其他号码: 】 | CL67: 4015.2 | CN67: 人民币 | CO67: 固定汇率 | CT67: 杭州-主城 | CW67: 否 | DD67: 未关闭 | DK67: 冯泽英 | DL67: 13094805606
A68: 现款现货收款单 | B68: SKD251005064 | C68: 杭州 | D68: 2025/10/9 | E68: 客户 | F68: 客户 | G68: 人民币 | H68: 1003.8 | I68: 1003.8 | J68: 杭州中冠电器有限公司 | L68: 杭州中冠电器有限公司 | M68: 滨江六空8090店 | N68: 杭州大区 | P68: 1003.8 | Q68: 葛芬 | R68: 人民币 | S68: 固定汇率 | T68: 1 | U68: 1003.8 | V68: 1003.8 | X68: 完全 | Z68: 销售业务 | AA68: 信用正常 | AB68: 转账 | AC68: 预收款 | AD68: 销售订单 | AE68: 1 | AF68: A20251005000961 | AG68: 1003.8 | AI68: 1003.8 | AJ68: 1003.8 | AM68: 1003.8 | AN68: 政府以旧换新中转银行 | AO68: 否 | AP68: 政府以旧换新中转银行 | AQ68: 手工新增 | AS68: 滨江六空8090店 | AX68: 1003.8 | AY68: 否 | AZ68: 9999999 | BA68: 1003.8 | BC68: 否 | BD68: 1003.8 | BE68: 完全 | BF68: 1003.8 | BH68: 1003.8 | BI68: 已审核 | BJ68: 葛 芬 | BK68: 葛 芬 | BL68: 桑玲 | BM68: 2025/10/5 | BN68: 2025-10-05 11:40:57 | BO68: 2025-10-06 12:54:57 | BR68: 否 | BS68: 1003.8 | BW68: 杭州中冠电器有限公司 | BX68: 1003.8 | BZ68: 人民币 | CA68: 否 | CB68: 2025/10/9 | CC68: 是 | CD68: DRSQ.00027 | CE68: EWH-80HGCWi薄型电热水器 | CF68: A20251005000961 | CG68: 1 | CH68: 否 | CK68: 10.4刷卡5019元(4015.2元+补贴1003.8元）（用户名 冯泽英）【用户姓名:冯泽英；用户手机:13094805606；其他号码: 】 | CL68: 1003.8 | CN68: 人民币 | CO68: 固定汇率 | CT68: 杭州-主城 | CW68: 否 | DD68: 未关闭 | DK68: 冯泽英 | DL68: 13094805606
A69: 现款现货收款单 | B69: SKD251006015 | C69: 杭州 | D69: 2025/10/5 | E69: 客户 | F69: 客户 | G69: 人民币 | H69: 5988 | I69: 5988 | J69: 杭州中冠电器有限公司 | L69: 杭州中冠电器有限公司 | M69: 杭州临平江南家居专卖店 | N69: 杭州大区 | P69: 5988 | Q69: 余亚炜 | R69: 人民币 | S69: 固定汇率 | T69: 1 | U69: 5988 | V69: 5988 | X69: 完全 | Z69: 销售业务 | AA69: 信用正常 | AB69: 转账 | AC69: 预收款 | AD69: 销售订单 | AE69: 1 | AF69: A20251005003831 | AG69: 5988 | AI69: 5988 | AJ69: 5988 | AM69: 5988 | AN69: 杭州中冠电器有限公司支付宝 | AO69: 否 | AP69: 杭州中冠电器有限公司支付宝 | AQ69: 手工新增 | AS69: 杭州临平江南家居专卖店 | AX69: 5988 | AY69: 否 | AZ69: hzzgcw@163.com | BA69: 5988 | BC69: 否 | BD69: 5988 | BE69: 完全 | BF69: 5988 | BH69: 5988 | BI69: 已审核 | BJ69: 余亚炜 | BK69: 余亚炜 | BL69: 桑玲 | BM69: 2025/10/6 | BN69: 2025-10-06 13:07:16 | BO69: 2025-10-06 14:25:26 | BR69: 否 | BS69: 5988 | BW69: 杭州中冠电器有限公司 | BX69: 5988 | BZ69: 人民币 | CA69: 否 | CB69: 2025/10/5 | CC69: 是 | CD69: RQRS.00010 | CE69: JSQ31-VJSAi燃气快速热水器（传统面板） | CF69: A20251005003831 | CG69: 1 | CH69: 否 | CK69: 10.5支付宝转账5988元【用户姓名:陈垚明；用户手机:1869000650；其他号码: 】 | CL69: 5988 | CN69: 人民币 | CO69: 固定汇率 | CT69: 杭州-余杭 | CW69: 否 | DD69: 未关闭 | DK69: 陈垚明 | DL69: 1869000650 | DR69: 2025100522001427851426692205
A70: 现款现货收款单 | B70: SKD251006017 | C70: 杭州 | D70: 2025/10/9 | E70: 客户 | F70: 客户 | G70: 人民币 | H70: 4351.15 | I70: 4325.04 | J70: 杭州中冠电器有限公司 | L70: 杭州中冠电器有限公司 | M70: 杭州红星美凯龙一号店 | N70: 杭州大区 | P70: 4351.15 | Q70: 吴红玉 | R70: 人民币 | S70: 固定汇率 | T70: 1 | U70: 4351.15 | V70: 4325.04 | X70: 完全 | Z70: 销售业务 | AA70: 信用正常 | AB70: 转账 | AC70: 预收款 | AD70: 销售订单 | AE70: 1 | AF70: A20251004002463 | AG70: 4351.15 | AI70: 4351.15 | AJ70: 4351.15 | AK70: 26.11 | AM70: 4325.04 | AN70: 杭州中冠电器有限公司 | AO70: 否 | AP70: 中信银行杭州钱江支行 | AQ70: 手工新增 | AS70: 杭州红星美凯龙一号店 | AX70: 4351.15 | AY70: 否 | AZ70: 7331710182200026317 | BA70: 4351.15 | BC70: 否 | BD70: 4351.15 | BE70: 完全 | BF70: 4351.15 | BG70: 26.11 | BH70: 4325.04 | BI70: 已审核 | BJ70: 陈联 | BK70: 桑玲 | BL70: 桑玲 | BM70: 2025/10/6 | BN70: 2025-10-07 09:55:13 | BO70: 2025-10-07 09:55:15 | BR70: 否 | BS70: 4351.15 | BW70: 杭州中冠电器有限公司 | BX70: 4351.15 | BZ70: 人民币 | CA70: 否 | CB70: 2025/10/9 | CC70: 是 | CD70: RQRS.00002 | CE70: JSQ31-LN燃气热水器 | CF70: A20251004002463 | CG70: 1 | CH70: 否 | CK70: 10.4刷卡5119元（4351.15+补贴767.85元）【用户姓名:李蒙；用户手机:18626892539；其他号码: 】 | CL70: 4351.15 | CN70: 人民币 | CO70: 固定汇率 | CT70: 杭州地区客户 | CW70: 否 | DD70: 未关闭 | DK70: 李蒙 | DL70: 18626892539
A71: 现款现货收款单 | B71: SKD251006018 | C71: 杭州 | D71: 2025/10/9 | E71: 客户 | F71: 客户 | G71: 人民币 | H71: 767.85 | I71: 767.85 | J71: 杭州中冠电器有限公司 | L71: 杭州中冠电器有限公司 | M71: 杭州红星美凯龙一号店 | N71: 杭州大区 | P71: 767.85 | Q71: 吴红玉 | R71: 人民币 | S71: 固定汇率 | T71: 1 | U71: 767.85 | V71: 767.85 | X71: 完全 | Z71: 销售业务 | AA71: 信用正常 | AB71: 转账 | AC71: 预收款 | AD71: 销售订单 | AE71: 1 | AF71: A20251004002463 | AG71: 767.85 | AI71: 767.85 | AJ71: 767.85 | AM71: 767.85 | AN71: 政府以旧换新中转银行 | AO71: 否 | AP71: 政府以旧换新中转银行 | AQ71: 手工新增 | AS71: 杭州红星美凯龙一号店 | AX71: 767.85 | AY71: 否 | AZ71: 9999999 | BA71: 767.85 | BC71: 否 | BD71: 767.85 | BE71: 完全 | BF71: 767.85 | BH71: 767.85 | BI71: 已审核 | BJ71: 陈联 | BK71: 陈联 | BL71: 桑玲 | BM71: 2025/10/6 | BN71: 2025-10-06 13:21:29 | BO71: 2025-10-07 09:55:29 | BR71: 否 | BS71: 767.85 | BW71: 杭州中冠电器有限公司 | BX71: 767.85 | BZ71: 人民币 | CA71: 否 | CB71: 2025/10/9 | CC71: 是 | CD71: RQRS.00002 | CE71: JSQ31-LN燃气热水器 | CF71: A20251004002463 | CG71: 1 | CH71: 否 | CK71: 10.4刷卡5119元（4351.15+补贴767.85元）【用户姓名:李蒙；用户手机:18626892539；其他号码: 】 | CL71: 767.85 | CN71: 人民币 | CO71: 固定汇率 | CT71: 杭州地区客户 | CW71: 否 | DD71: 未关闭 | DK71: 李蒙 | DL71: 18626892539
A72: 现款现货收款单 | B72: SKD251006019 | C72: 杭州 | D72: 2025/10/5 | E72: 客户 | F72: 客户 | G72: 人民币 | H72: 3998 | I72: 3998 | J72: 杭州中冠电器有限公司 | L72: 杭州中冠电器有限公司 | M72: 杭州红星美凯龙一号店 | N72: 杭州大区 | P72: 3998 | Q72: 吴红玉 | R72: 人民币 | S72: 固定汇率 | T72: 1 | U72: 3998 | V72: 3998 | X72: 完全 | Z72: 销售业务 | AA72: 信用正常 | AB72: 转账 | AC72: 预收款 | AD72: 销售订单 | AE72: 1 | AF72: A20251005000626 | AG72: 3998 | AI72: 3998 | AJ72: 3998 | AM72: 3998 | AN72: 杭州中冠电器有限公司支付宝 | AO72: 否 | AP72: 杭州中冠电器有限公司支付宝 | AQ72: 手工新增 | AS72: 杭州红星美凯龙一号店 | AX72: 3998 | AY72: 否 | AZ72: hzzgcw@163.com | BA72: 3998 | BC72: 否 | BD72: 3998 | BE72: 完全 | BF72: 3998 | BH72: 3998 | BI72: 已审核 | BJ72: 陈联 | BK72: 陈联 | BL72: 桑玲 | BM72: 2025/10/6 | BN72: 2025-10-06 13:26:13 | BO72: 2025-10-06 14:25:50 | BR72: 否 | BS72: 3998 | BW72: 杭州中冠电器有限公司 | BX72: 3998 | BZ72: 人民币 | CA72: 否 | CB72: 2025/10/5 | CC72: 是 | CD72: DR.00103 | CE72: EWH-60DA储水式电热水器 | CF72: A20251005000626 | CG72: 1 | CH72: 否 | CK72: 10.5支付宝3998元【用户姓名:高骏；用户手机:13335711339；其他号码: 】 | CL72: 3998 | CN72: 人民币 | CO72: 固定汇率 | CT72: 杭州地区客户 | CW72: 否 | DD72: 未关闭 | DK72: 高骏 | DL72: 13335711339 | DR72: 2025100522001424201415448887
A73: 现款现货收款单 | B73: SKD251006020 | C73: 杭州 | D73: 2025/10/5 | E73: 客户 | F73: 客户 | G73: 人民币 | H73: 828 | I73: 828 | J73: 杭州中冠电器有限公司 | L73: 杭州中冠电器有限公司 | M73: 杭州红星美凯龙一号店 | N73: 杭州大区 | P73: 828 | Q73: 吴红玉 | R73: 人民币 | S73: 固定汇率 | T73: 1 | U73: 828 | V73: 828 | X73: 完全 | Z73: 销售业务 | AA73: 信用正常 | AB73: 转账 | AC73: 预收款 | AD73: 销售订单 | AE73: 1 | AF73: A20251005001561 | AG73: 828 | AI73: 828 | AJ73: 828 | AM73: 828 | AN73: 杭州中冠电器有限公司支付宝 | AO73: 否 | AP73: 杭州中冠电器有限公司支付宝 | AQ73: 手工新增 | AS73: 杭州红星美凯龙一号店 | AX73: 828 | AY73: 否 | AZ73: hzzgcw@163.com | BA73: 828 | BC73: 否 | BD73: 828 | BE73: 完全 | BF73: 828 | BH73: 828 | BI73: 已审核 | BJ73: 陈联 | BK73: 陈联 | BL73: 桑玲 | BM73: 2025/10/6 | BN73: 2025-10-06 13:32:19 | BO73: 2025-10-06 14:26:07 | BR73: 否 | BS73: 828 | BW73: 杭州中冠电器有限公司 | BX73: 828 | BZ73: 人民币 | CA73: 否 | CB73: 2025/10/5 | CC73: 是 | CD73: DR.00133 | CE73: EWH-6B2储水式电热水器 | CF73: A20251005001561 | CG73: 1 | CH73: 否 | CK73: 10.5支付宝828元【用户姓名:王永林；用户手机:18968906210；其他号码: 】 | CL73: 828 | CN73: 人民币 | CO73: 固定汇率 | CT73: 杭州地区客户 | CW73: 否 | DD73: 未关闭 | DK73: 王永林 | DL73: 18968906210 | DR73: 2025100522001457641445790253
A74: 现款现货收款单 | B74: SKD251006021 | C74: 杭州 | D74: 2025/10/5 | E74: 客户 | F74: 客户 | G74: 人民币 | H74: 3869 | I74: 3869 | J74: 杭州中冠电器有限公司 | L74: 杭州中冠电器有限公司 | M74: 杭州红星美凯龙一号店 | N74: 杭州大区 | P74: 3869 | Q74: 吴红玉 | R74: 人民币 | S74: 固定汇率 | T74: 1 | U74: 3869 | V74: 3869 | X74: 完全 | Z74: 销售业务 | AA74: 信用正常 | AB74: 转账 | AC74: 预收款 | AD74: 销售订单 | AE74: 1 | AF74: A20251005003812 | AG74: 3869 | AI74: 3869 | AJ74: 3869 | AM74: 3869 | AN74: 杭州中冠电器有限公司支付宝 | AO74: 否 | AP74: 杭州中冠电器有限公司支付宝 | AQ74: 手工新增 | AS74: 杭州红星美凯龙一号店 | AX74: 3869 | AY74: 否 | AZ74: hzzgcw@163.com | BA74: 3869 | BC74: 否 | BD74: 3869 | BE74: 完全 | BF74: 3869 | BH74: 3869 | BI74: 已审核 | BJ74: 陈联 | BK74: 陈联 | BL74: 桑玲 | BM74: 2025/10/6 | BN74: 2025-10-06 13:35:18 | BO74: 2025-10-06 14:26:30 | BR74: 否 | BS74: 3869 | BW74: 杭州中冠电器有限公司 | BX74: 3869 | BZ74: 人民币 | CA74: 否 | CB74: 2025/10/5 | CC74: 是 | CD74: DR.00103 | CE74: EWH-60DA储水式电热水器 | CF74: A20251005003812 | CG74: 1 | CH74: 否 | CK74: 10.5支付宝3869元【用户姓名:周国成；用户手机:15805710535；其他号码: 】 | CL74: 3869 | CN74: 人民币 | CO74: 固定汇率 | CT74: 杭州地区客户 | CW74: 否 | DD74: 未关闭 | DK74: 周国成 | DL74: 15805710535 | DR74: '2025100522001439511449364436
A75: 销售收款单 | B75: SKD251006027 | C75: 杭州 | D75: 2025/10/6 | E75: 客户 | F75: 客户 | G75: 人民币 | H75: 35000 | I75: 35000 | J75: 杭州中冠电器有限公司 | L75: 杭州中冠电器有限公司 | M75: 桐庐佳尼特水处理设备有限公司 | N75: 杭州大区 | P75: 35000 | Q75: 吴海林 | R75: 人民币 | S75: 固定汇率 | T75: 1 | U75: 35000 | V75: 35000 | X75: 空 | Z75: 销售业务 | AA75: 信用正常 | AB75: 转账 | AC75: 销售收款 | AE75: 1 | AG75: 35000 | AI75: 35000 | AJ75: 35000 | AM75: 35000 | AN75: 杭州中冠电器有限公司 | AO75: 否 | AP75: 中信银行杭州钱江支行 | AQ75: 手工新增 | AS75: 桐庐佳尼特水处理设备有限公司 | AX75: 35000 | AY75: 否 | AZ75: 7331710182200026317 | BA75: 35000 | BC75: 否 | BE75: 空 | BH75: 35000 | BI75: 已审核 | BJ75: 陈联 | BK75: 陈联 | BL75: 桑玲 | BM75: 2025/10/6 | BN75: 2025-10-06 13:59:54 | BO75: 2025-10-06 14:28:47 | BR75: 否 | BS75: 35000 | BW75: 杭州中冠电器有限公司 | BZ75: 人民币 | CA75: 否 | CB75: 2025/10/6 | CC75: 是 | CH75: 否 | CK75: 10.6转账35000元【用户姓名: ；用户手机: ；其他号码: 】 | CN75: 人民币 | CO75: 固定汇率 | CT75: 杭州-桐庐 | CW75: 否 | DD75: 未关闭
A76: 现款现货收款单 | B76: SKD251006030 | C76: 杭州 | D76: 2025/10/3 | E76: 客户 | F76: 客户 | G76: 人民币 | H76: 1999 | I76: 1999 | J76: 杭州中冠电器有限公司 | L76: 杭州中冠电器有限公司 | M76: 杭州红星美凯龙一号店 | N76: 杭州大区 | P76: 1999 | Q76: 吴红玉 | R76: 人民币 | S76: 固定汇率 | T76: 1 | U76: 1999 | V76: 1999 | X76: 完全 | Z76: 销售业务 | AA76: 信用正常 | AB76: 转账 | AC76: 预收款 | AD76: 销售订单 | AE76: 1 | AF76: A20251004001948 | AG76: 1999 | AI76: 1999 | AJ76: 1999 | AM76: 1999 | AN76: 杭州中冠电器有限公司支付宝 | AO76: 否 | AP76: 杭州中冠电器有限公司支付宝 | AQ76: 手工新增 | AS76: 杭州红星美凯龙一号店 | AX76: 1999 | AY76: 否 | AZ76: hzzgcw@163.com | BA76: 1999 | BC76: 否 | BD76: 1999 | BE76: 完全 | BF76: 1999 | BH76: 1999 | BI76: 已审核 | BJ76: 陈联 | BK76: 陈联 | BL76: 桑玲 | BM76: 2025/10/6 | BN76: 2025-10-06 14:25:43 | BO76: 2025-10-06 14:27:20 | BR76: 否 | BS76: 1999 | BW76: 杭州中冠电器有限公司 | BX76: 1999 | BZ76: 人民币 | CA76: 否 | CB76: 2025/10/3 | CC76: 是 | CD76: DR.00184 | CE76: CTE-80J1佳尼特电热水器 | CF76: A20251004001948 | CG76: 1 | CH76: 否 | CK76: 10.3支付宝1999元【用户姓名:姜文东；用户手机:13857108921；其他号码: 】 | CL76: 1999 | CN76: 人民币 | CO76: 固定汇率 | CT76: 杭州地区客户 | CW76: 否 | DD76: 未关闭 | DK76: 姜文东 | DL76: 13857108921 | DR76: '2025100322001404301430791680
A77: 现款现货收款单 | B77: SKD251006031 | C77: 杭州 | D77: 2025/10/3 | E77: 客户 | F77: 客户 | G77: 人民币 | H77: 350 | I77: 350 | J77: 杭州中冠电器有限公司 | L77: 杭州中冠电器有限公司 | M77: 萧山第六空间专卖店 | N77: 杭州大区 | P77: 350 | Q77: 徐美娟 | R77: 人民币 | S77: 固定汇率 | T77: 1 | U77: 350 | V77: 350 | X77: 完全 | Z77: 销售业务 | AA77: 信用正常 | AB77: 转账 | AC77: 预收款 | AD77: 销售订单 | AE77: 1 | AF77: A20251003003449 | AG77: 350 | AI77: 350 | AJ77: 350 | AM77: 350 | AN77: 杭州中冠电器有限公司支付宝 | AO77: 否 | AP77: 杭州中冠电器有限公司支付宝 | AQ77: 手工新增 | AS77: 萧山第六空间专卖店 | AX77: 350 | AY77: 否 | AZ77: hzzgcw@163.com | BA77: 350 | BC77: 否 | BD77: 350 | BE77: 完全 | BF77: 350 | BH77: 350 | BI77: 已审核 | BJ77: 陈联 | BK77: 陈联 | BL77: 桑玲 | BM77: 2025/10/6 | BN77: 2025-10-06 14:43:59 | BO77: 2025-10-06 15:06:20 | BR77: 否 | BS77: 350 | BW77: 杭州中冠电器有限公司 | BX77: 350 | BZ77: 人民币 | CA77: 否 | CB77: 2025/10/3 | CC77: 是 | CD77: JS.00037 | CE77: PF25C1前置过滤器 | CF77: A20251003003449 | CG77: 1 | CH77: 否 | CK77: 10.3支付宝350元【用户姓名:曾城洲；用户手机:18988475722；其他号码: 】 | CL77: 350 | CN77: 人民币 | CO77: 固定汇率 | CT77: 杭州-萧山 | CW77: 否 | DD77: 未关闭 | DK77: 曾城洲 | DL77: 18988475722 | DR77: 2025100322001483231432801313
A78: 现款现货收款单 | B78: SKD251006032 | C78: 杭州 | D78: 2025/10/3 | E78: 客户 | F78: 客户 | G78: 人民币 | H78: 3395 | I78: 3395 | J78: 杭州中冠电器有限公司 | L78: 杭州中冠电器有限公司 | M78: 萧山第六空间专卖店 | N78: 杭州大区 | P78: 3395 | Q78: 徐美娟 | R78: 人民币 | S78: 固定汇率 | T78: 1 | U78: 3395 | V78: 3395 | X78: 完全 | Z78: 销售业务 | AA78: 信用正常 | AB78: 转账 | AC78: 预收款 | AD78: 销售订单 | AE78: 1 | AF78: A20251003003447 | AG78: 3395 | AI78: 3395 | AJ78: 3395 | AM78: 3395 | AN78: 杭州中冠电器有限公司支付宝 | AO78: 否 | AP78: 杭州中冠电器有限公司支付宝 | AQ78: 手工新增 | AS78: 萧山第六空间专卖店 | AX78: 3395 | AY78: 否 | AZ78: hzzgcw@163.com | BA78: 3395 | BC78: 否 | BD78: 3395 | BE78: 完全 | BF78: 3395 | BH78: 3395 | BI78: 已审核 | BJ78: 陈联 | BK78: 陈联 | BL78: 桑玲 | BM78: 2025/10/6 | BN78: 2025-10-06 14:44:35 | BO78: 2025-10-06 15:06:35 | BR78: 否 | BS78: 3395 | BW78: 杭州中冠电器有限公司 | BX78: 3395 | BZ78: 人民币 | CA78: 否 | CB78: 2025/10/3 | CC78: 是 | CD78: YSJ.00042 | CE78: R1700FWi饮水机 | CF78: A20251003003447 | CG78: 1 | CH78: 否 | CK78: 10.3支付宝3395元【用户姓名:曾城洲；用户手机:18988475722；其他号码: 】 | CL78: 3395 | CN78: 人民币 | CO78: 固定汇率 | CT78: 杭州-萧山 | CW78: 否 | DD78: 未关闭 | DK78: 曾城洲 | DL78: 18988475722 | DR78: 2025100322001483231430072112
A79: 现款现货收款单 | B79: SKD251006034 | C79: 杭州 | D79: 2025/10/6 | E79: 客户 | F79: 客户 | G79: 人民币 | H79: 3395 | I79: 3395 | J79: 杭州中冠电器有限公司 | L79: 杭州中冠电器有限公司 | M79: 杭州红星美凯龙一号店 | N79: 杭州大区 | P79: 3395 | Q79: 吴红玉 | R79: 人民币 | S79: 固定汇率 | T79: 1 | U79: 3395 | V79: 3395 | X79: 完全 | Z79: 销售业务 | AA79: 信用正常 | AB79: 支付宝 | AC79: 预收款 | AD79: 销售订单 | AE79: 1 | AF79: A20251006000832 | AG79: 3395 | AI79: 3395 | AJ79: 3395 | AM79: 3395 | AN79: 杭州中冠电器有限公司支付宝 | AO79: 否 | AP79: 杭州中冠电器有限公司支付宝 | AQ79: 手工新增 | AS79: 杭州红星美凯龙一号店 | AX79: 3395 | AY79: 否 | AZ79: hzzgcw@163.com | BA79: 3395 | BC79: 否 | BD79: 3395 | BE79: 完全 | BF79: 3395 | BH79: 3395 | BI79: 已审核 | BJ79: 陈联 | BK79: 陈联 | BL79: 桑玲 | BM79: 2025/10/6 | BN79: 2025-10-06 14:46:42 | BO79: 2025-10-06 15:06:56 | BR79: 否 | BS79: 3395 | BW79: 杭州中冠电器有限公司 | BX79: 3395 | BZ79: 人民币 | CA79: 否 | CB79: 2025/10/6 | CC79: 是 | CD79: YSJ.00042 | CE79: R1700FWi饮水机 | CF79: A20251006000832 | CG79: 1 | CH79: 否 | CK79: 10.6支付宝3395元【用户姓名:何志鹏；用户手机:15868169479；其他号码: 】 | CL79: 3395 | CN79: 人民币 | CO79: 固定汇率 | CT79: 杭州地区客户 | CW79: 否 | DD79: 未关闭 | DK79: 何志鹏 | DL79: 15868169479 | DR79: '2025100622001463731420729190
A80: 现款现货收款单 | B80: SKD251006048 | C80: 杭州 | D80: 2025/10/6 | E80: 客户 | F80: 客户 | G80: 人民币 | H80: 3998 | I80: 3998 | J80: 杭州中冠电器有限公司 | L80: 杭州中冠电器有限公司 | M80: 杭州红星美凯龙一号店 | N80: 杭州大区 | P80: 3998 | Q80: 吴红玉 | R80: 人民币 | S80: 固定汇率 | T80: 1 | U80: 3998 | V80: 3998 | X80: 完全 | Z80: 销售业务 | AA80: 信用正常 | AB80: 转账 | AC80: 预收款 | AD80: 销售订单 | AE80: 1 | AF80: A20251006003074 | AG80: 3998 | AI80: 3998 | AJ80: 3998 | AM80: 3998 | AN80: 杭州中冠电器有限公司支付宝 | AO80: 否 | AP80: 杭州中冠电器有限公司支付宝 | AQ80: 手工新增 | AS80: 杭州红星美凯龙一号店 | AX80: 3998 | AY80: 否 | AZ80: hzzgcw@163.com | BA80: 3998 | BC80: 否 | BD80: 3998 | BE80: 完全 | BF80: 3998 | BH80: 3998 | BI80: 已审核 | BJ80: 陈联 | BK80: 陈联 | BL80: 桑玲 | BM80: 2025/10/6 | BN80: 2025-10-06 15:52:17 | BO80: 2025-10-07 09:55:53 | BR80: 否 | BS80: 3998 | BW80: 杭州中冠电器有限公司 | BX80: 3998 | BZ80: 人民币 | CA80: 否 | CB80: 2025/10/6 | CC80: 是 | CD80: DR.00104 | CE80: EWH-80DA储水式电热水器 | CF80: A20251006003074 | CG80: 1 | CH80: 否 | CK80: 10.6支付宝3998【用户姓名:叶成光；用户手机:13867460339；其他号码: 】 | CL80: 3998 | CN80: 人民币 | CO80: 固定汇率 | CT80: 杭州地区客户 | CW80: 否 | DD80: 未关闭 | DK80: 叶成光 | DL80: 13867460339 | DR80: 2025100622001406721457173777
A81: 现款现货收款单 | B81: SKD251007024 | C81: 杭州 | D81: 2025/10/6 | E81: 客户 | F81: 客户 | G81: 人民币 | H81: 3091 | I81: 3091 | J81: 杭州中冠电器有限公司 | L81: 杭州中冠电器有限公司 | M81: 杭州红星美凯龙一号店 | N81: 杭州大区 | P81: 3091 | Q81: 吴红玉 | R81: 人民币 | S81: 固定汇率 | T81: 1 | U81: 3091 | V81: 3091 | X81: 完全 | Z81: 销售业务 | AA81: 信用正常 | AB81: 转账 | AC81: 预收款 | AD81: 销售订单 | AE81: 1 | AF81: A20251006003379 | AG81: 3091 | AI81: 3091 | AJ81: 3091 | AM81: 3091 | AN81: 杭州中冠电器有限公司支付宝 | AO81: 否 | AP81: 杭州中冠电器有限公司支付宝 | AQ81: 手工新增 | AS81: 杭州红星美凯龙一号店 | AX81: 3091 | AY81: 否 | AZ81: hzzgcw@163.com | BA81: 3091 | BC81: 否 | BD81: 3091 | BE81: 完全 | BF81: 3091 | BH81: 3091 | BI81: 已审核 | BJ81: 陈联 | BK81: 陈联 | BL81: 桑玲 | BM81: 2025/10/7 | BN81: 2025-10-07 08:32:23 | BO81: 2025-10-07 09:56:33 | BR81: 否 | BS81: 3091 | BW81: 杭州中冠电器有限公司 | BX81: 3091 | BZ81: 人民币 | CA81: 否 | CB81: 2025/10/6 | CC81: 是 | CD81: DRSQ.00067 | CE81: CEWH-60D1Wi储水电热水器 | CF81: A20251006003379 | CG81: 1 | CH81: 否 | CK81: 10.6支付宝3091元【用户姓名:吕祝平；用户手机:13306810636；其他号码: 】 | CL81: 3091 | CN81: 人民币 | CO81: 固定汇率 | CT81: 杭州地区客户 | CW81: 否 | DD81: 未关闭 | DK81: 吕祝平 | DL81: 13306810636 | DR81: 2025100622001446031447301883
A82: 现款现货收款单 | B82: SKD251007074 | C82: 杭州 | D82: 2025/10/9 | E82: 客户 | F82: 客户 | G82: 人民币 | H82: 2863.2 | I82: 2846.02 | J82: 杭州中冠电器有限公司 | L82: 杭州中冠电器有限公司 | M82: 滨江六空8090店 | N82: 杭州大区 | P82: 2863.2 | Q82: 葛芬 | R82: 人民币 | S82: 固定汇率 | T82: 1 | U82: 2863.2 | V82: 2846.02 | X82: 完全 | Z82: 销售业务 | AA82: 信用正常 | AB82: 转账 | AC82: 预收款 | AD82: 销售订单 | AE82: 1 | AF82: A20250926001718C | AG82: 2863.2 | AI82: 2863.2 | AJ82: 2863.2 | AK82: 17.18 | AM82: 2846.02 | AN82: 杭州中冠电器有限公司 | AO82: 否 | AP82: 中信银行杭州钱江支行 | AQ82: 手工新增 | AS82: 滨江六空8090店 | AX82: 2863.2 | AY82: 否 | AZ82: 7331710182200026317 | BA82: 2863.2 | BC82: 否 | BD82: 2863.2 | BE82: 完全 | BF82: 2863.2 | BG82: 17.18 | BH82: 2846.02 | BI82: 已审核 | BJ82: 陈联 | BK82: 桑玲 | BL82: 桑玲 | BM82: 2025/10/7 | BN82: 2025-10-07 09:57:00 | BO82: 2025-10-07 09:57:02 | BR82: 否 | BS82: 2863.2 | BW82: 杭州中冠电器有限公司 | BX82: 2863.2 | BZ82: 人民币 | CA82: 否 | CB82: 2025/10/9 | CC82: 是 | CD82: DRSQ.00061 | CE82: CEWH-60D5BWi储水式热水器 | CF82: A20250926001718C | CG82: 1 | CH82: 否 | CK82: 10.5刷卡3579元（2863.2元+补贴715.8元）【用户姓名:吴健；用户手机:18668139761；其他号码: 】 | CL82: 2863.2 | CN82: 人民币 | CO82: 固定汇率 | CT82: 杭州-主城 | CW82: 否 | DD82: 未关闭 | DK82: 吴健 | DL82: 18668139761
A83: 现款现货收款单 | B83: SKD251007075 | C83: 杭州 | D83: 2025/10/9 | E83: 客户 | F83: 客户 | G83: 人民币 | H83: 715.8 | I83: 715.8 | J83: 杭州中冠电器有限公司 | L83: 杭州中冠电器有限公司 | M83: 滨江六空8090店 | N83: 杭州大区 | P83: 715.8 | Q83: 葛芬 | R83: 人民币 | S83: 固定汇率 | T83: 1 | U83: 715.8 | V83: 715.8 | X83: 完全 | Z83: 销售业务 | AA83: 信用正常 | AB83: 转账 | AC83: 预收款 | AD83: 销售订单 | AE83: 1 | AF83: A20250926001718C | AG83: 715.8 | AI83: 715.8 | AJ83: 715.8 | AM83: 715.8 | AN83: 政府以旧换新中转银行 | AO83: 否 | AP83: 政府以旧换新中转银行 | AQ83: 手工新增 | AS83: 滨江六空8090店 | AX83: 715.8 | AY83: 否 | AZ83: 9999999 | BA83: 715.8 | BC83: 否 | BD83: 715.8 | BE83: 完全 | BF83: 715.8 | BH83: 715.8 | BI83: 已审核 | BJ83: 陈联 | BK83: 陈联 | BL83: 桑玲 | BM83: 2025/10/7 | BN83: 2025-10-07 09:18:58 | BO83: 2025-10-07 09:57:17 | BR83: 否 | BS83: 715.8 | BW83: 杭州中冠电器有限公司 | BX83: 715.8 | BZ83: 人民币 | CA83: 否 | CB83: 2025/10/9 | CC83: 是 | CD83: DRSQ.00061 | CE83: CEWH-60D5BWi储水式热水器 | CF83: A20250926001718C | CG83: 1 | CH83: 否 | CK83: 10.5刷卡3579元（2863.2元+补贴715.8元）【用户姓名:吴健；用户手机:18668139761；其他号码: 】 | CL83: 715.8 | CN83: 人民币 | CO83: 固定汇率 | CT83: 杭州-主城 | CW83: 否 | DD83: 未关闭 | DK83: 吴健 | DL83: 18668139761
A84: 销售收款单 | B84: SKD251007108 | C84: 杭州 | D84: 2025/10/7 | E84: 客户 | F84: 客户 | G84: 人民币 | H84: 4590 | I84: 4590 | J84: 杭州中冠电器有限公司 | L84: 杭州中冠电器有限公司 | M84: 杭州装家百科电器有限公司 | N84: 杭州大区 | P84: 4590 | Q84: 黄颖 | R84: 人民币 | S84: 固定汇率 | T84: 1 | U84: 4590 | V84: 4590 | X84: 空 | Z84: 销售业务 | AA84: 信用正常 | AB84: 转账 | AC84: 销售收款 | AE84: 1 | AG84: 4590 | AI84: 4590 | AJ84: 4590 | AM84: 4590 | AN84: 杭州中冠电器有限公司 | AO84: 否 | AP84: 中信银行杭州钱江支行 | AQ84: 手工新增 | AS84: 杭州装家百科电器有限公司 | AX84: 4590 | AY84: 否 | AZ84: 7331710182200026317 | BA84: 4590 | BC84: 否 | BE84: 空 | BH84: 4590 | BI84: 已审核 | BJ84: 陈联 | BK84: 陈联 | BL84: 桑玲 | BM84: 2025/10/7 | BN84: 2025-10-07 09:44:30 | BO84: 2025-10-07 10:00:03 | BR84: 否 | BS84: 4590 | BW84: 杭州中冠电器有限公司 | BZ84: 人民币 | CA84: 否 | CB84: 2025/10/7 | CC84: 是 | CH84: 否 | CK84: 10.7转账4590元【用户姓名: ；用户手机: ；其他号码: 】 | CN84: 人民币 | CO84: 固定汇率 | CT84: 杭州-主城 | CW84: 否 | DD84: 未关闭
A85: 销售收款单 | B85: SKD251007183 | C85: 杭州 | D85: 2025/10/7 | E85: 客户 | F85: 客户 | G85: 人民币 | H85: 11696 | I85: 11619.97 | J85: 杭州中冠电器有限公司 | L85: 杭州中冠电器有限公司 | M85: 自营以旧换新特别账户 | N85: 销管部 | P85: 11696 | Q85: 罗清 | R85: 人民币 | S85: 固定汇率 | T85: 1 | U85: 11696 | V85: 11619.97 | X85: 空 | Z85: 销售业务 | AA85: 信用正常 | AB85: 转账 | AC85: 销售收款 | AE85: 1 | AG85: 2574 | AI85: 11696 | AJ85: 2574 | AK85: 16.73 | AM85: 2557.27 | AN85: 杭州中冠电器有限公司 | AO85: 否 | AP85: 中信银行杭州钱江支行 | AQ85: 手工新增 | AS85: 自营以旧换新特别账户 | AX85: 2574 | AY85: 否 | AZ85: 7331710182200026317 | BA85: 2574 | BB85: 2025年10月周女士结算(换新35） | BC85: 否 | BE85: 空 | BG85: 16.73 | BH85: 2557.27 | BI85: 已审核 | BJ85: 毛银萍 | BK85: 桑玲 | BL85: 桑玲 | BM85: 2025/10/7 | BN85: 2025-10-07 15:25:22 | BO85: 2025-10-07 15:25:24 | BR85: 否 | BS85: 2574 | BW85: 杭州中冠电器有限公司 | BZ85: 人民币 | CA85: 否 | CB85: 2025/10/7 | CC85: 是 | CH85: 否 | CK85: 2025年10月7日中信银行收款【用户姓名:2025年10月结算(换新35-38）；用户手机: ；其他号码: 】 | CN85: 人民币 | CO85: 固定汇率 | CT85: 杭州-主城 | CW85: 否 | DD85: 未关闭 | DK85: 2025年10月结算(换新35-38） | DR85: 2025年10月结算(换新35-38）
AB86: 转账 | AC86: 销售收款 | AG86: 3460 | AJ86: 3460 | AK86: 22.49 | AM86: 3437.51 | AN86: 杭州中冠电器有限公司 | AP86: 中信银行杭州钱江支行 | AX86: 3460 | AZ86: 7331710182200026317 | BA86: 3460 | BB86: 2025年10月客户结算(换新36） | BC86: 否 | BE86: 空 | BG86: 22.49 | BH86: 3437.51 | BS86: 3460 | CB86: 2025/10/7 | CC86: 是 | DD86: 未关闭
AB87: 转账 | AC87: 销售收款 | AG87: 2686 | AJ87: 2686 | AK87: 17.46 | AM87: 2668.54 | AN87: 杭州中冠电器有限公司 | AP87: 中信银行杭州钱江支行 | AX87: 2686 | AZ87: 7331710182200026317 | BA87: 2686 | BB87: 2025年10月孙女士结算(换新37） | BC87: 否 | BE87: 空 | BG87: 17.46 | BH87: 2668.54 | BS87: 2686 | CB87: 2025/10/7 | CC87: 是 | DD87: 未关闭
AB88: 转账 | AC88: 销售收款 | AG88: 2976 | AJ88: 2976 | AK88: 19.35 | AM88: 2956.65 | AN88: 杭州中冠电器有限公司 | AP88: 中信银行杭州钱江支行 | AX88: 2976 | AZ88: 7331710182200026317 | BA88: 2976 | BB88: 2025年10月章女士结算(换新38） | BC88: 否 | BE88: 空 | BG88: 19.35 | BH88: 2956.65 | BS88: 2976 | CB88: 2025/10/7 | CC88: 是 | DD88: 未关闭
A89: 销售收款单 | B89: SKD251007184 | C89: 杭州 | D89: 2025/10/8 | E89: 客户 | F89: 客户 | G89: 人民币 | H89: 2172 | I89: 2157.88 | J89: 杭州中冠电器有限公司 | L89: 杭州中冠电器有限公司 | M89: 自营以旧换新特别账户 | N89: 销管部 | P89: 2172 | Q89: 罗清 | R89: 人民币 | S89: 固定汇率 | T89: 1 | U89: 2172 | V89: 2157.88 | X89: 空 | Z89: 销售业务 | AA89: 信用正常 | AB89: 转账 | AC89: 销售收款 | AE89: 1 | AG89: 2172 | AI89: 2172 | AJ89: 2172 | AK89: 14.12 | AM89: 2157.88 | AN89: 杭州中冠电器有限公司 | AO89: 否 | AP89: 中信银行杭州钱江支行 | AQ89: 手工新增 | AS89: 自营以旧换新特别账户 | AX89: 2172 | AY89: 否 | AZ89: 7331710182200026317 | BA89: 2172 | BB89: 2025年10月客户结算(换新39） | BC89: 否 | BE89: 空 | BG89: 14.12 | BH89: 2157.88 | BI89: 已审核 | BJ89: 毛银萍 | BK89: 桑玲 | BL89: 桑玲 | BM89: 2025/10/7 | BN89: 2025-10-10 09:04:45 | BO89: 2025-10-10 09:04:46 | BR89: 否 | BS89: 2172 | BW89: 杭州中冠电器有限公司 | BZ89: 人民币 | CA89: 否 | CB89: 2025/10/8 | CC89: 是 | CH89: 否 | CK89: 2025年10月8日中信银行收款【用户姓名:2025年10月结算(换新39）；用户手机: ；其他号码: 】 | CN89: 人民币 | CO89: 固定汇率 | CT89: 杭州-主城 | CW89: 否 | DD89: 未关闭 | DK89: 2025年10月结算(换新39） | DR89: 2025年10月结算(换新39）
A90: 销售收款单 | B90: SKD251007193 | C90: 杭州 | D90: 2025/10/7 | E90: 客户 | F90: 客户 | G90: 人民币 | H90: 1397.6 | I90: 1397.6 | J90: 杭州中冠电器有限公司 | L90: 杭州中冠电器有限公司 | M90: 杭州华东家电市场铁人电器商行 | N90: 杭州大区 | P90: 1397.6 | Q90: 黄颖 | R90: 人民币 | S90: 固定汇率 | T90: 1 | U90: 1397.6 | V90: 1397.6 | X90: 空 | Z90: 销售业务 | AA90: 信用正常 | AB90: 转账 | AC90: 销售收款 | AE90: 1 | AG90: 1397.6 | AI90: 1397.6 | AJ90: 1397.6 | AM90: 1397.6 | AN90: 杭州中冠电器有限公司 | AO90: 否 | AP90: 中信银行杭州钱江支行 | AQ90: 手工新增 | AS90: 杭州华东家电市场铁人电器商行 | AX90: 1397.6 | AY90: 否 | AZ90: 7331710182200026317 | BA90: 1397.6 | BC90: 否 | BE90: 空 | BH90: 1397.6 | BI90: 已审核 | BJ90: 陈联 | BK90: 陈联 | BL90: 桑玲 | BM90: 2025/10/7 | BN90: 2025-10-07 10:49:24 | BO90: 2025-10-07 15:06:33 | BR90: 否 | BS90: 1397.6 | BW90: 杭州中冠电器有限公司 | BZ90: 人民币 | CA90: 否 | CB90: 2025/10/7 | CC90: 是 | CH90: 否 | CK90: 10.7转账1397.60元【用户姓名:祝振权；用户手机: ；其他号码: 】 | CN90: 人民币 | CO90: 固定汇率 | CT90: 杭州-主城 | CW90: 否 | DD90: 未关闭 | DK90: 祝振权
A91: 现款现货收款单 | B91: SKD251007195 | C91: 杭州 | D91: 2025/10/6 | E91: 客户 | F91: 客户 | G91: 人民币 | H91: 79610 | I91: 79610 | J91: 杭州中冠电器有限公司 | L91: 杭州中冠电器有限公司 | M91: 杭州金蝶零售 | N91: 销管部 | P91: 79610 | Q91: 何云锋 | R91: 人民币 | S91: 固定汇率 | T91: 1 | U91: 79610 | V91: 79610 | X91: 完全 | Z91: 销售业务 | AA91: 信用正常 | AB91: 转账 | AC91: 预收款 | AD91: 销售订单 | AE91: 1 | AF91: XSDD251007001 | AG91: 79610 | AI91: 79610 | AJ91: 79610 | AM91: 79610 | AN91: 杭州中冠电器有限公司 | AO91: 否 | AP91: 中信银行杭州钱江支行 | AQ91: 手工新增 | AS91: 杭州金蝶零售 | AX91: 79610 | AY91: 否 | AZ91: 7331710182200026317 | BA91: 79610 | BC91: 否 | BD91: 79610 | BE91: 完全 | BF91: 79610 | BH91: 79610 | BI91: 已审核 | BJ91: 陈联 | BK91: 陈联 | BL91: 桑玲 | BM91: 2025/10/7 | BN91: 2025-10-07 10:51:50 | BO91: 2025-10-07 15:06:51 | BR91: 否 | BS91: 79610 | BW91: 杭州中冠电器有限公司 | BX91: 79610 | BZ91: 人民币 | CA91: 否 | CB91: 2025/10/6 | CC91: 是 | CD91: JS.09.00010 | CE91: BZR100-A2111 | CF91: XSDD251007001 | CG91: 1 | CH91: 否 | CK91: 10.6转账79610元【用户姓名:浙江本越环保科技有限公司；用户手机:18815151934；其他号码: 】 | CL91: 79610 | CN91: 人民币 | CO91: 固定汇率 | CT91: 杭州-主城 | CW91: 否 | DD91: 未关闭 | DK91: 浙江本越环保科技有限公司 | DL91: 18815151934
A92: 现款现货收款单 | B92: SKD251007204 | C92: 杭州 | D92: 2025/10/7 | E92: 客户 | F92: 客户 | G92: 人民币 | H92: 5667 | I92: 5667 | J92: 杭州中冠电器有限公司 | L92: 杭州中冠电器有限公司 | M92: 杭州红星美凯龙一号店 | N92: 杭州大区 | P92: 5667 | Q92: 吴红玉 | R92: 人民币 | S92: 固定汇率 | T92: 1 | U92: 5667 | V92: 5667 | X92: 完全 | Z92: 销售业务 | AA92: 信用正常 | AB92: 转账 | AC92: 预收款 | AD92: 销售订单 | AE92: 1 | AF92: A20251007001009 | AG92: 5667 | AI92: 5667 | AJ92: 5667 | AM92: 5667 | AN92: 杭州中冠电器有限公司支付宝 | AO92: 否 | AP92: 杭州中冠电器有限公司支付宝 | AQ92: 手工新增 | AS92: 杭州红星美凯龙一号店 | AX92: 5667 | AY92: 否 | AZ92: hzzgcw@163.com | BA92: 5667 | BC92: 否 | BD92: 5667 | BE92: 完全 | BF92: 5667 | BH92: 5667 | BI92: 已审核 | BJ92: 陈联 | BK92: 陈联 | BL92: 桑玲 | BM92: 2025/10/7 | BN92: 2025-10-07 11:05:10 | BO92: 2025-10-07 15:16:16 | BR92: 否 | BS92: 5667 | BW92: 杭州中冠电器有限公司 | BX92: 5667 | BZ92: 人民币 | CA92: 否 | CB92: 2025/10/7 | CC92: 是 | CD92: DR.00011-1 | CE92: EWH-40MINIwi储水式电热水器 | CF92: A20251007001009 | CG92: 1 | CH92: 否 | CK92: 10.7支付宝5667元【用户姓名:周红燕；用户手机:13858079575；其他号码: 】 | CL92: 5667 | CN92: 人民币 | CO92: 固定汇率 | CT92: 杭州地区客户 | CW92: 否 | DD92: 未关闭 | DK92: 周红燕 | DL92: 13858079575 | DR92: 2025100722001409581452386654
A93: 现款现货收款单 | B93: SKD251007330 | C93: 杭州 | D93: 2025/10/7 | E93: 客户 | F93: 客户 | G93: 人民币 | H93: 4791 | I93: 4791 | J93: 杭州中冠电器有限公司 | L93: 杭州中冠电器有限公司 | M93: 萧山第六空间专卖店 | N93: 杭州大区 | P93: 4791 | Q93: 徐美娟 | R93: 人民币 | S93: 固定汇率 | T93: 1 | U93: 4791 | V93: 4791 | X93: 完全 | Z93: 销售业务 | AA93: 信用正常 | AB93: 转账 | AC93: 预收款 | AD93: 销售订单 | AE93: 1 | AF93: A20251007001686 | AG93: 4791 | AI93: 4791 | AJ93: 4791 | AM93: 4791 | AN93: 杭州中冠电器有限公司支付宝 | AO93: 否 | AP93: 杭州中冠电器有限公司支付宝 | AQ93: 手工新增 | AS93: 萧山第六空间专卖店 | AX93: 4791 | AY93: 否 | AZ93: hzzgcw@163.com | BA93: 4791 | BC93: 否 | BD93: 4791 | BE93: 完全 | BF93: 4791 | BH93: 4791 | BI93: 已审核 | BJ93: 徐美娟 | BK93: 陈联 | BL93: 桑玲 | BM93: 2025/10/7 | BN93: 2025-10-07 12:31:16 | BO93: 2025-10-07 15:16:46 | BR93: 否 | BS93: 4791 | BW93: 杭州中冠电器有限公司 | BX93: 4791 | BZ93: 人民币 | CA93: 否 | CB93: 2025/10/7 | CC93: 是 | CD93: YSJ.00030 | CE93: R1600DWWi净水机 | CF93: A20251007001686 | CG93: 1 | CH93: 否 | CK93: 10.7支付宝转账4791元【用户姓名:项延杰；用户手机:15561836777；其他号码: 】 | CL93: 4791 | CN93: 人民币 | CO93: 固定汇率 | CT93: 杭州-萧山 | CW93: 否 | DD93: 未关闭 | DK93: 项延杰 | DL93: 15561836777 | DR93: 2025100722001480941429674315
A94: 现款现货收款单 | B94: SKD251007372 | C94: 杭州 | D94: 2025/10/6 | E94: 客户 | F94: 客户 | G94: 人民币 | H94: 790 | I94: 790 | J94: 杭州中冠电器有限公司 | L94: 杭州中冠电器有限公司 | M94: 滨江六空8090店 | N94: 杭州大区 | P94: 790 | Q94: 葛芬 | R94: 人民币 | S94: 固定汇率 | T94: 1 | U94: 790 | V94: 790 | X94: 完全 | Z94: 销售业务 | AA94: 信用正常 | AB94: 转账 | AC94: 预收款 | AD94: 销售订单 | AE94: 1 | AF94: A20251006003903 | AG94: 790 | AI94: 790 | AJ94: 790 | AM94: 790 | AN94: 杭州中冠电器有限公司支付宝 | AO94: 否 | AP94: 杭州中冠电器有限公司支付宝 | AQ94: 手工新增 | AS94: 滨江六空8090店 | AX94: 790 | AY94: 否 | AZ94: hzzgcw@163.com | BA94: 790 | BC94: 否 | BD94: 790 | BE94: 完全 | BF94: 790 | BH94: 790 | BI94: 已审核 | BJ94: 葛 芬 | BK94: 葛 芬 | BL94: 桑玲 | BM94: 2025/10/7 | BN94: 2025-10-07 15:16:50 | BO94: 2025-10-07 15:17:43 | BR94: 否 | BS94: 790 | BW94: 杭州中冠电器有限公司 | BX94: 790 | BZ94: 人民币 | CA94: 否 | CB94: 2025/10/6 | CC94: 是 | CD94: DR.00133 | CE94: EWH-6B2储水式电热水器 | CF94: A20251006003903 | CG94: 1 | CH94: 否 | CK94: 10.6支付宝转账790元（用户名 陈金才）【用户姓名:陈金才；用户手机:15088600687；其他号码: 】 | CL94: 790 | CN94: 人民币 | CO94: 固定汇率 | CT94: 杭州-主城 | CW94: 否 | DD94: 未关闭 | DK94: 陈金才 | DL94: 15088600687 | DR94: 2025100622001422151440873414
A95: 现款现货收款单 | B95: SKD251007422 | C95: 杭州 | D95: 2025/10/4 | E95: 客户 | F95: 客户 | G95: 人民币 | H95: 5872 | I95: 5859.38 | J95: 杭州中冠电器有限公司 | L95: 杭州中冠电器有限公司 | M95: 杭州红星美凯龙一号店 | N95: 杭州大区 | P95: 5872 | Q95: 吴红玉 | R95: 人民币 | S95: 固定汇率 | T95: 1 | U95: 5872 | V95: 5859.38 | X95: 完全 | Z95: 销售业务 | AA95: 信用正常 | AB95: 扫码牌 | AC95: 预收款 | AD95: 销售订单 | AE95: 1 | AF95: A20251004001971 | AG95: 5872 | AI95: 5872 | AJ95: 5872 | AK95: 12.62 | AM95: 5859.38 | AN95: 杭州中冠电器有限公司 | AO95: 否 | AP95: 中信银行杭州钱江支行 | AQ95: 手工新增 | AS95: 杭州红星美凯龙一号店 | AX95: 5872 | AY95: 否 | AZ95: 7331710182200026317 | BA95: 5872 | BC95: 否 | BD95: 5872 | BE95: 完全 | BF95: 5872 | BG95: 12.62 | BH95: 5859.38 | BI95: 已审核 | BJ95: 陈联 | BK95: 桑玲 | BL95: 桑玲 | BM95: 2025/10/7 | BN95: 2025-10-07 15:07:37 | BO95: 2025-10-07 15:07:38 | BR95: 否 | BS95: 5872 | BW95: 杭州中冠电器有限公司 | BX95: 5872 | BZ95: 人民币 | CA95: 否 | CB95: 2025/10/4 | CC95: 是 | CD95: YSJ.00014 | CE95: DR1600HF2Ai反渗透净水机 | CF95: A20251004001971 | CG95: 1 | CH95: 否 | CK95: 10.3扫码付5872元【用户姓名:周海英；用户手机:15888840126；其他号码: 】 | CL95: 5872 | CN95: 人民币 | CO95: 固定汇率 | CT95: 杭州地区客户 | CW95: 否 | DD95: 未关闭 | DK95: 周海英 | DL95: 15888840126
A96: 现款现货收款单 | B96: SKD251007424 | C96: 杭州 | D96: 2025/10/6 | E96: 客户 | F96: 客户 | G96: 人民币 | H96: 5872 | I96: 5859.38 | J96: 杭州中冠电器有限公司 | L96: 杭州中冠电器有限公司 | M96: 滨江六空8090店 | N96: 杭州大区 | P96: 5872 | Q96: 葛芬 | R96: 人民币 | S96: 固定汇率 | T96: 1 | U96: 5872 | V96: 5859.38 | X96: 完全 | Z96: 销售业务 | AA96: 信用正常 | AB96: 扫码牌 | AC96: 预收款 | AD96: 销售订单 | AE96: 1 | AF96: A20251005004370 | AG96: 5872 | AI96: 5872 | AJ96: 5872 | AK96: 12.62 | AM96: 5859.38 | AN96: 杭州中冠电器有限公司 | AO96: 否 | AP96: 中信银行杭州钱江支行 | AQ96: 手工新增 | AS96: 滨江六空8090店 | AX96: 5872 | AY96: 否 | AZ96: 7331710182200026317 | BA96: 5872 | BC96: 否 | BD96: 5872 | BE96: 完全 | BF96: 5872 | BG96: 12.62 | BH96: 5859.38 | BI96: 已审核 | BJ96: 陈联 | BK96: 桑玲 | BL96: 桑玲 | BM96: 2025/10/7 | BN96: 2025-10-07 15:08:12 | BO96: 2025-10-07 15:08:13 | BR96: 否 | BS96: 5872 | BW96: 杭州中冠电器有限公司 | BX96: 5872 | BZ96: 人民币 | CA96: 否 | CB96: 2025/10/6 | CC96: 是 | CD96: YSJ.00014 | CE96: DR1600HF2Ai反渗透净水机 | CF96: A20251005004370 | CG96: 1 | CH96: 否 | CK96: 10.5扫码付5872元【用户姓名:马遇伯；用户手机:15267076317；其他号码: 】 | CL96: 5872 | CN96: 人民币 | CO96: 固定汇率 | CT96: 杭州-主城 | CW96: 否 | DD96: 未关闭 | DK96: 马遇伯 | DL96: 15267076317
A97: 销售收款单 | B97: SKD251007427 | C97: 金华 | D97: 2025/10/7 | E97: 客户 | F97: 客户 | G97: 人民币 | H97: 8362 | I97: 8362 | J97: 杭州中冠电器有限公司 | L97: 杭州中冠电器有限公司 | M97: 义乌颖亿贸易有限公司 | N97: 金华办事处 | P97: 8362 | Q97: 林青云 | R97: 人民币 | S97: 固定汇率 | T97: 1 | U97: 8362 | V97: 8362 | X97: 空 | Z97: 销售业务 | AA97: 信用正常 | AB97: 转账 | AC97: 销售收款 | AE97: 1 | AG97: 8362 | AI97: 8362 | AJ97: 8362 | AM97: 8362 | AN97: 杭州中冠电器有限公司 | AO97: 否 | AP97: 中信银行杭州钱江支行 | AQ97: 手工新增 | AS97: 义乌颖亿贸易有限公司 | AX97: 8362 | AY97: 否 | AZ97: 7331710182200026317 | BA97: 8362 | BC97: 否 | BE97: 空 | BH97: 8362 | BI97: 已审核 | BJ97: 王小婷 | BK97: 王小婷 | BL97: 桑玲 | BM97: 2025/10/7 | BN97: 2025-10-07 15:07:06 | BO97: 2025-10-07 15:08:32 | BR97: 否 | BS97: 8362 | BW97: 杭州中冠电器有限公司 | BZ97: 人民币 | CA97: 否 | CB97: 2025/10/7 | CC97: 是 | CH97: 否 | CK97: 2025.10.7杭州中信8362【用户姓名:义乌颖亿贸易有限公司；用户手机: ；其他号码: 】 | CN97: 人民币 | CO97: 固定汇率 | CT97: 金华-义乌 | CW97: 否 | DD97: 未关闭 | DK97: 义乌颖亿贸易有限公司
A98: 现款现货收款单 | B98: SKD251007433 | C98: 杭州 | D98: 2025/10/9 | E98: 客户 | F98: 客户 | G98: 人民币 | H98: 3519.2 | I98: 3498.08 | J98: 杭州中冠电器有限公司 | L98: 杭州中冠电器有限公司 | M98: 滨江六空8090店 | N98: 杭州大区 | P98: 3519.2 | Q98: 葛芬 | R98: 人民币 | S98: 固定汇率 | T98: 1 | U98: 3519.2 | V98: 3498.08 | X98: 完全 | Z98: 销售业务 | AA98: 信用正常 | AB98: 刷卡 | AC98: 预收款 | AD98: 销售订单 | AE98: 1 | AF98: A20251007002192 | AG98: 3519.2 | AI98: 3519.2 | AJ98: 3519.2 | AK98: 21.12 | AM98: 3498.08 | AN98: 杭州中冠电器有限公司 | AO98: 否 | AP98: 中信银行杭州钱江支行 | AQ98: 手工新增 | AS98: 滨江六空8090店 | AX98: 3519.2 | AY98: 否 | AZ98: 7331710182200026317 | BA98: 3519.2 | BC98: 否 | BD98: 3519.2 | BE98: 完全 | BF98: 3519.2 | BG98: 21.12 | BH98: 3498.08 | BI98: 已审核 | BJ98: 葛 芬 | BK98: 桑玲 | BL98: 桑玲 | BM98: 2025/10/7 | BN98: 2025-10-08 14:14:04 | BO98: 2025-10-08 14:14:05 | BR98: 否 | BS98: 3519.2 | BW98: 杭州中冠电器有限公司 | BX98: 3519.2 | BZ98: 人民币 | CA98: 否 | CB98: 2025/10/9 | CC98: 是 | CD98: DRSQ.00026 | CE98: EWH-60HGCWi薄型电热水器 | CF98: A20251007002192 | CG98: 1 | CH98: 否 | CK98: 10. 6刷卡4399元(3519.2元+补贴879.8元）（用户名 陆思岚）【用户姓名:陆思岚；用户手机:13606562973；其他号码: 】 | CL98: 3519.2 | CN98: 人民币 | CO98: 固定汇率 | CT98: 杭州-主城 | CW98: 否 | DD98: 未关闭 | DK98: 陆思岚 | DL98: 13606562973
A99: 现款现货收款单 | B99: SKD251007434 | C99: 杭州 | D99: 2025/10/9 | E99: 客户 | F99: 客户 | G99: 人民币 | H99: 879.8 | I99: 879.8 | J99: 杭州中冠电器有限公司 | L99: 杭州中冠电器有限公司 | M99: 滨江六空8090店 | N99: 杭州大区 | P99: 879.8 | Q99: 葛芬 | R99: 人民币 | S99: 固定汇率 | T99: 1 | U99: 879.8 | V99: 879.8 | X99: 完全 | Z99: 销售业务 | AA99: 信用正常 | AB99: 刷卡 | AC99: 预收款 | AD99: 销售订单 | AE99: 1 | AF99: A20251007002192 | AG99: 879.8 | AI99: 879.8 | AJ99: 879.8 | AM99: 879.8 | AN99: 政府以旧换新中转银行 | AO99: 否 | AP99: 政府以旧换新中转银行 | AQ99: 手工新增 | AS99: 滨江六空8090店 | AX99: 879.8 | AY99: 否 | AZ99: 9999999 | BA99: 879.8 | BC99: 否 | BD99: 879.8 | BE99: 完全 | BF99: 879.8 | BH99: 879.8 | BI99: 已审核 | BJ99: 葛 芬 | BK99: 葛 芬 | BL99: 桑玲 | BM99: 2025/10/7 | BN99: 2025-10-07 15:50:12 | BO99: 2025-10-08 14:14:13 | BR99: 否 | BS99: 879.8 | BW99: 杭州中冠电器有限公司 | BX99: 879.8 | BZ99: 人民币 | CA99: 否 | CB99: 2025/10/9 | CC99: 是 | CD99: DRSQ.00026 | CE99: EWH-60HGCWi薄型电热水器 | CF99: A20251007002192 | CG99: 1 | CH99: 否 | CK99: 10. 6刷卡4399元(3519.2元+补贴879.8元）（用户名 陆思岚）【用户姓名:陆思岚；用户手机:13606562973；其他号码: 】 | CL99: 879.8 | CN99: 人民币 | CO99: 固定汇率 | CT99: 杭州-主城 | CW99: 否 | DD99: 未关闭 | DK99: 陆思岚 | DL99: 13606562973
A100: 现款现货收款单 | B100: SKD251008031 | C100: 杭州 | D100: 2025/10/7 | E100: 客户 | F100: 客户 | G100: 人民币 | H100: 7270 | I100: 7254.37 | J100: 杭州中冠电器有限公司 | L100: 杭州中冠电器有限公司 | M100: （新）滨江第六空间专卖店 | N100: 杭州大区 | P100: 7270 | Q100: 谢士英 | R100: 人民币 | S100: 固定汇率 | T100: 1 | U100: 7270 | V100: 7254.37 | X100: 完全 | Z100: 销售业务 | AA100: 信用正常 | AB100: 转账 | AC100: 预收款 | AD100: 销售订单 | AE100: 1 | AF100: A20251006002215 | AG100: 7270 | AI100: 7270 | AJ100: 7270 | AK100: 15.63 | AM100: 7254.37 | AN100: 杭州中冠电器有限公司 | AO100: 否 | AP100: 中信银行杭州钱江支行 | AQ100: 手工新增 | AS100: （新）滨江第六空间专卖店 | AX100: 7270 | AY100: 否 | AZ100: 7331710182200026317 | BA100: 7270 | BC100: 否 | BD100: 7270 | BE100: 完全 | BF100: 7270 | BG100: 15.63 | BH100: 7254.37 | BI100: 已审核 | BJ100: 谢士英 | BK100: 桑玲 | BL100: 桑玲 | BM100: 2025/10/8 | BN100: 2025-10-08 15:56:07 | BO100: 2025-10-08 15:56:08 | BR100: 否 | BS100: 7270 | BW100: 杭州中冠电器有限公司 | BX100: 7270 | BZ100: 人民币 | CA100: 否 | CB100: 2025/10/7 | CC100: 是 | CD100: RR.00026 | CE100: JSQ33-MJSX燃气热水器 | CF100: A20251006002215 | CG100: 1 | CH100: 否 | CK100: 10.6扫码付7270元【用户姓名:杨利月；用户手机:13275120002；其他号码: 】 | CL100: 7270 | CN100: 人民币 | CO100: 固定汇率 | CT100: 杭州-主城 | CW100: 否 | DD100: 未关闭 | DK100: 杨利月 | DL100: 13275120002
...
